{"learner":{"attributes":{"scikit_learn":"{\"_estimator_type\": \"classifier\"}"},"feature_names":[],"feature_types":[],"gradient_booster":{"model":{"gbtree_model_param":{"num_parallel_tree":"1","num_trees":"100"},"iteration_indptr":[0,1,2,3,4,5,6,7,8,9,10,11,12,13,14,15,16,17,18,19,20,21,22,23,24,25,26,27,28,29,30,31,32,33,34,35,36,37,38,39,40,41,42,43,44,45,46,47,48,49,50,51,52,53,54,55,56,57,58,59,60,61,62,63,64,65,66,67,68,69,70,71,72,73,74,75,76,77,78,79,80,81,82,83,84,85,86,87,88,89,90,91,92,93,94,95,96,97,98,99,100],"tree_info":[0,0,0,0,0,0,0,0,0,0,0,0,0,0,0,0,0,0,0,0,0,0,0,0,0,0,0,0,0,0,0,0,0,0,0,0,0,0,0,0,0,0,0,0,0,0,0,0,0,0,0,0,0,0,0,0,0,0,0,0,0,0,0,0,0,0,0,0,0,0,0,0,0,0,0,0,0,0,0,0,0,0,0,0,0,0,0,0,0,0,0,0,0,0,0,0,0,0,0,0],"trees":[{"base_weights":[-1.0758374E0,-9.962128E-3,-1.10345595E-1],"categories":[],"categories_nodes":[],"categories_segments":[],"categories_sizes":[],"default_left":[0,0,0],"id":0,"left_children":[1,-1,-1],"loss_changes":[8.3153915E-1,0E0,0E0],"parents":[2147483647,0,0],"right_children":[2,-1,-1],"split_conditions":[1.7630485E-1,-9.962128E-3,-1.10345595E-1],"split_indices":[28,0,0],"split_type":[0,0,0],"sum_hessian":[3.3918766E1,1.0599614E0,3.2858803E1],"tree_param":{"num_deleted":"0","num_feature":"2048","num_nodes":"3","size_leaf_vector":"1"}},{"base_weights":[-1.0572882E0,-9.4882855E-3,-1.0867142E-1],"categories":[],"categories_nodes":[],"categories_segments":[],"categories_sizes":[],"default_left":[0,0,0],"id":1,"left_children":[1,-1,-1],"loss_changes":[8.097229E-1,0E0,0E0],"parents":[2147483647,0,0],"right_children":[2,-1,-1],"split_conditions":[1.7630485E-1,-9.4882855E-3,-1.0867142E-1],"split_indices":[28,0,0],"split_type":[0,0,0],"sum_hessian":[3.1233107E1,1.0519664E0,3.018114E1],"tree_param":{"num_deleted":"0","num_feature":"2048","num_nodes":"3","size_leaf_vector":"1"}},{"base_weights":[-1.0399804E0,-1.072145E-1,-6.431172E-3],"categories":[],"categories_nodes":[],"categories_segments":[],"categories_sizes":[],"default_left":[0,0,0],"id":2,"left_children":[1,-1,-1],"loss_changes":[8.6426926E-1,0E0,0E0],"parents":[2147483647,0,0],"right_children":[2,-1,-1],"split_conditions":[1.4507107E0,-1.072145E-1,-6.431172E-3],"split_indices":[511,0,0],"split_type":[0,0,0],"sum_hessian":[2.8737535E1,2.7724665E1,1.0128721E0],"tree_param":{"num_deleted":"0","num_feature":"2048","num_nodes":"3","size_leaf_vector":"1"}},{"base_weights":[-1.0235449E0,-5.37313E-3,-1.0583909E-1],"categories":[],"categories_nodes":[],"categories_segments":[],"categories_sizes":[],"default_left":[0,0,0],"id":3,"left_children":[1,-1,-1],"loss_changes":[8.699837E-1,0E0,0E0],"parents":[2147483647,0,0],"right_children":[2,-1,-1],"split_conditions":[1.5028714E-1,-5.37313E-3,-1.0583909E-1],"split_indices":[55,0,0],"split_type":[0,0,0],"sum_hessian":[2.6426638E1,1.0047557E0,2.5421883E1],"tree_param":{"num_deleted":"0","num_feature":"2048","num_nodes":"3","size_leaf_vector":"1"}},{"base_weights":[-1.0078216E0,-4.8688026E-3,-1.04545295E-1],"categories":[],"categories_nodes":[],"categories_segments":[],"categories_sizes":[],"default_left":[0,0,0],"id":4,"left_children":[1,-1,-1],"loss_changes":[8.619919E-1,0E0,0E0],"parents":[2147483647,0,0],"right_children":[2,-1,-1],"split_conditions":[2.7560124E-1,-4.8688026E-3,-1.04545295E-1],"split_indices":[65,0,0],"split_type":[0,0,0],"sum_hessian":[2.429252E1,1.0037266E0,2.3288795E1],"tree_param":{"num_deleted":"0","num_feature":"2048","num_nodes":"3","size_leaf_vector":"1"}},{"base_weights":[-9.9264807E-1,-4.410077E-3,-1.03324786E-1],"categories":[],"categories_nodes":[],"categories_segments":[],"categories_sizes":[],"default_left":[0,0,0],"id":5,"left_children":[1,-1,-1],"loss_changes":[8.527374E-1,0E0,0E0],"parents":[2147483647,0,0],"right_children":[2,-1,-1],"split_conditions":[2.094856E-1,-4.410077E-3,-1.03324786E-1],"split_indices":[223,0,0],"split_type":[0,0,0],"sum_hessian":[2.2326008E1,1.0020059E0,2.1324001E1],"tree_param":{"num_deleted":"0","num_feature":"2048","num_nodes":"3","size_leaf_vector":"1"}},{"base_weights":[-9.778712E-1,-4.004494E-3,-1.0216291E-1],"categories":[],"categories_nodes":[],"categories_segments":[],"categories_sizes":[],"default_left":[0,0,0],"id":6,"left_children":[1,-1,-1],"loss_changes":[8.4210205E-1,0E0,0E0],"parents":[2147483647,0,0],"right_children":[2,-1,-1],"split_conditions":[1.052562E-1,-4.004494E-3,-1.0216291E-1],"split_indices":[50,0,0],"split_type":[0,0,0],"sum_hessian":[2.051733E1,1.0000147E0,1.9517317E1],"tree_param":{"num_deleted":"0","num_feature":"2048","num_nodes":"3","size_leaf_vector":"1"}},{"base_weights":[-9.633566E-1,-1.010465E-1,-3.8180226E-3],"categories":[],"categories_nodes":[],"categories_segments":[],"categories_sizes":[],"default_left":[0,0,0],"id":7,"left_children":[1,-1,-1],"loss_changes":[8.2684135E-1,0E0,0E0],"parents":[2147483647,0,0],"right_children":[2,-1,-1],"split_conditions":[6.721025E-1,-1.010465E-1,-3.8180226E-3],"split_indices":[1041,0,0],"split_type":[0,0,0],"sum_hessian":[1.8856556E1,1.7855213E1,1.0013423E0],"tree_param":{"num_deleted":"0","num_feature":"2048","num_nodes":"3","size_leaf_vector":"1"}},{"base_weights":[-9.489872E-1,-9.9988714E-2,-3.3792239E-3],"categories":[],"categories_nodes":[],"categories_segments":[],"categories_sizes":[],"default_left":[0,0,0],"id":8,"left_children":[1,-1,-1],"loss_changes":[8.202667E-1,0E0,0E0],"parents":[2147483647,0,0],"right_children":[2,-1,-1],"split_conditions":[9.8443097E-1,-9.9988714E-2,-3.3792239E-3],"split_indices":[588,0,0],"split_type":[0,0,0],"sum_hessian":[1.7333921E1,1.6332996E1,1.0009243E0],"tree_param":{"num_deleted":"0","num_feature":"2048","num_nodes":"3","size_leaf_vector":"1"}},{"base_weights":[-9.346217E-1,-9.892644E-2,-3.1888937E-3],"categories":[],"categories_nodes":[],"categories_segments":[],"categories_sizes":[],"default_left":[0,0,0],"id":9,"left_children":[1,-1,-1],"loss_changes":[8.040705E-1,0E0,0E0],"parents":[2147483647,0,0],"right_children":[2,-1,-1],"split_conditions":[6.779481E-1,-9.892644E-2,-3.1888937E-3],"split_indices":[1405,0,0],"split_type":[0,0,0],"sum_hessian":[1.5940109E1,1.4939936E1,1.0001733E0],"tree_param":{"num_deleted":"0","num_feature":"2048","num_nodes":"3","size_leaf_vector":"1"}},{"base_weights":[-9.202127E-1,-9.7901426E-2,-2.959825E-3],"categories":[],"categories_nodes":[],"categories_segments":[],"categories_sizes":[],"default_left":[0,0,0],"id":10,"left_children":[1,-1,-1],"loss_changes":[7.913952E-1,0E0,0E0],"parents":[2147483647,0,0],"right_children":[2,-1,-1],"split_conditions":[5.0005215E-1,-9.7901426E-2,-2.959825E-3],"split_indices":[263,0,0],"split_type":[0,0,0],"sum_hessian":[1.4665079E1,1.3663695E1,1.0013833E0],"tree_param":{"num_deleted":"0","num_feature":"2048","num_nodes":"3","size_leaf_vector":"1"}},{"base_weights":[-9.05649E-1,-2.773186E-3,-9.686262E-2],"categories":[],"categories_nodes":[],"categories_segments":[],"categories_sizes":[],"default_left":[0,0,0],"id":11,"left_children":[1,-1,-1],"loss_changes":[7.748432E-1,0E0,0E0],"parents":[2147483647,0,0],"right_children":[2,-1,-1],"split_conditions":[1.6434442E-1,-2.773186E-3,-9.686262E-2],"split_indices":[1092,0,0],"split_type":[0,0,0],"sum_hessian":[1.350031E1,1.0000281E0,1.2500281E1],"tree_param":{"num_deleted":"0","num_feature":"2048","num_nodes":"3","size_leaf_vector":"1"}},{"base_weights":[-8.9089453E-1,-9.5852785E-2,-2.5622265E-3],"categories":[],"categories_nodes":[],"categories_segments":[],"categories_sizes":[],"default_left":[0,0,0],"id":12,"left_children":[1,-1,-1],"loss_changes":[7.617731E-1,0E0,0E0],"parents":[2147483647,0,0],"right_children":[2,-1,-1],"split_conditions":[6.068107E-1,-9.5852785E-2,-2.5622265E-3],"split_indices":[299,0,0],"split_type":[0,0,0],"sum_hessian":[1.2436708E1,1.1435115E1,1.0015932E0],"tree_param":{"num_deleted":"0","num_feature":"2048","num_nodes":"3","size_leaf_vector":"1"}},{"base_weights":[-8.7585104E-1,-9.480395E-2,-2.4151148E-3],"categories":[],"categories_nodes":[],"categories_segments":[],"categories_sizes":[],"default_left":[0,0,0],"id":13,"left_children":[1,-1,-1],"loss_changes":[7.435961E-1,0E0,0E0],"parents":[2147483647,0,0],"right_children":[2,-1,-1],"split_conditions":[7.8195363E-1,-9.480395E-2,-2.4151148E-3],"split_indices":[639,0,0],"split_type":[0,0,0],"sum_hessian":[1.1466772E1,1.0466535E1,1.000238E0],"tree_param":{"num_deleted":"0","num_feature":"2048","num_nodes":"3","size_leaf_vector":"1"}},{"base_weights":[-8.605199E-1,-2.2682564E-3,-9.37669E-2],"categories":[],"categories_nodes":[],"categories_segments":[],"categories_sizes":[],"default_left":[0,0,0],"id":14,"left_children":[1,-1,-1],"loss_changes":[7.273884E-1,0E0,0E0],"parents":[2147483647,0,0],"right_children":[2,-1,-1],"split_conditions":[2.0187013E-1,-2.2682564E-3,-9.37669E-2],"split_indices":[501,0,0],"split_type":[0,0,0],"sum_hessian":[1.0582234E1,1.001372E0,9.580862E0],"tree_param":{"num_deleted":"0","num_feature":"2048","num_nodes":"3","size_leaf_vector":"1"}},{"base_weights":[-8.448331E-1,-9.2685126E-2,-2.1583731E-3],"categories":[],"categories_nodes":[],"categories_segments":[],"categories_sizes":[],"default_left":[0,0,0],"id":15,"left_children":[1,-1,-1],"loss_changes":[7.076359E-1,0E0,0E0],"parents":[2147483647,0,0],"right_children":[2,-1,-1],"split_conditions":[8.12422E-1,-9.2685126E-2,-2.1583731E-3],"split_indices":[178,0,0],"split_type":[0,0,0],"sum_hessian":[9.7764435E0,8.776244E0,1.0001991E0],"tree_param":{"num_deleted":"0","num_feature":"2048","num_nodes":"3","size_leaf_vector":"1"}},{"base_weights":[-8.2880473E-1,-2.0074297E-3,-9.1613725E-2],"categories":[],"categories_nodes":[],"categories_segments":[],"categories_sizes":[],"default_left":[0,0,0],"id":16,"left_children":[1,-1,-1],"loss_changes":[6.908803E-1,0E0,0E0],"parents":[2147483647,0,0],"right_children":[2,-1,-1],"split_conditions":[1.8447675E-1,-2.0074297E-3,-9.1613725E-2],"split_indices":[829,0,0],"split_type":[0,0,0],"sum_hessian":[9.042295E0,1.001149E0,8.041146E0],"tree_param":{"num_deleted":"0","num_feature":"2048","num_nodes":"3","size_leaf_vector":"1"}},{"base_weights":[-8.123795E-1,-9.049174E-2,-1.9061562E-3],"categories":[],"categories_nodes":[],"categories_segments":[],"categories_sizes":[],"default_left":[0,0,0],"id":17,"left_children":[1,-1,-1],"loss_changes":[6.709242E-1,0E0,0E0],"parents":[2147483647,0,0],"right_children":[2,-1,-1],"split_conditions":[5.514507E-1,-9.049174E-2,-1.9061562E-3],"split_indices":[1880,0,0],"split_type":[0,0,0],"sum_hessian":[8.374127E0,7.3733735E0,1.0007541E0],"tree_param":{"num_deleted":"0","num_feature":"2048","num_nodes":"3","size_leaf_vector":"1"}},{"base_weights":[-7.9558736E-1,-1.8151532E-3,-8.935403E-2],"categories":[],"categories_nodes":[],"categories_segments":[],"categories_sizes":[],"default_left":[0,0,0],"id":18,"left_children":[1,-1,-1],"loss_changes":[6.513214E-1,0E0,0E0],"parents":[2147483647,0,0],"right_children":[2,-1,-1],"split_conditions":[2.2301659E-1,-1.8151532E-3,-8.935403E-2],"split_indices":[813,0,0],"split_type":[0,0,0],"sum_hessian":[7.765881E0,1.001607E0,6.764274E0],"tree_param":{"num_deleted":"0","num_feature":"2048","num_nodes":"3","size_leaf_vector":"1"}},{"base_weights":[-7.7841973E-1,-8.816847E-2,-1.7056089E-3],"categories":[],"categories_nodes":[],"categories_segments":[],"categories_sizes":[],"default_left":[0,0,0],"id":19,"left_children":[1,-1,-1],"loss_changes":[6.306472E-1,0E0,0E0],"parents":[2147483647,0,0],"right_children":[2,-1,-1],"split_conditions":[5.985282E-1,-8.816847E-2,-1.7056089E-3],"split_indices":[277,0,0],"split_type":[0,0,0],"sum_hessian":[7.2124996E0,6.2119317E0,1.0005677E0],"tree_param":{"num_deleted":"0","num_feature":"2048","num_nodes":"3","size_leaf_vector":"1"}},{"base_weights":[-7.6091564E-1,-8.695664E-2,-1.600127E-3],"categories":[],"categories_nodes":[],"categories_segments":[],"categories_sizes":[],"default_left":[0,0,0],"id":20,"left_children":[1,-1,-1],"loss_changes":[6.100068E-1,0E0,0E0],"parents":[2147483647,0,0],"right_children":[2,-1,-1],"split_conditions":[7.390506E-1,-8.695664E-2,-1.600127E-3],"split_indices":[1057,0,0],"split_type":[0,0,0],"sum_hessian":[6.708868E0,5.708856E0,1.000012E0],"tree_param":{"num_deleted":"0","num_feature":"2048","num_nodes":"3","size_leaf_vector":"1"}},{"base_weights":[-7.430939E-1,-8.571171E-2,-1.5334048E-3],"categories":[],"categories_nodes":[],"categories_segments":[],"categories_sizes":[],"default_left":[0,0,0],"id":21,"left_children":[1,-1,-1],"loss_changes":[5.885248E-1,0E0,0E0],"parents":[2147483647,0,0],"right_children":[2,-1,-1],"split_conditions":[6.0347074E-1,-8.571171E-2,-1.5334048E-3],"split_indices":[1310,0,0],"split_type":[0,0,0],"sum_hessian":[6.2506294E0,5.2502837E0,1.0003453E0],"tree_param":{"num_deleted":"0","num_feature":"2048","num_nodes":"3","size_leaf_vector":"1"}},{"base_weights":[-7.24988E-1,-8.442469E-2,-1.4704431E-3],"categories":[],"categories_nodes":[],"categories_segments":[],"categories_sizes":[],"default_left":[0,0,0],"id":22,"left_children":[1,-1,-1],"loss_changes":[5.664575E-1,0E0,0E0],"parents":[2147483647,0,0],"right_children":[2,-1,-1],"split_conditions":[7.2935134E-1,-8.442469E-2,-1.4704431E-3],"split_indices":[268,0,0],"split_type":[0,0,0],"sum_hessian":[5.8337593E0,4.83358E0,1.0001793E0],"tree_param":{"num_deleted":"0","num_feature":"2048","num_nodes":"3","size_leaf_vector":"1"}},{"base_weights":[-7.0664895E-1,-8.3107315E-2,-1.4130584E-3],"categories":[],"categories_nodes":[],"categories_segments":[],"categories_sizes":[],"default_left":[0,0,0],"id":23,"left_children":[1,-1,-1],"loss_changes":[5.4440856E-1,0E0,0E0],"parents":[2147483647,0,0],"right_children":[2,-1,-1],"split_conditions":[7.590928E-1,-8.3107315E-2,-1.4130584E-3],"split_indices":[1465,0,0],"split_type":[0,0,0],"sum_hessian":[5.454425E0,4.4540887E0,1.0003362E0],"tree_param":{"num_deleted":"0","num_feature":"2048","num_nodes":"3","size_leaf_vector":"1"}},{"base_weights":[-6.8812126E-1,-1.3577233E-3,-8.1749104E-2],"categories":[],"categories_nodes":[],"categories_segments":[],"categories_sizes":[],"default_left":[0,0,0],"id":24,"left_children":[1,-1,-1],"loss_changes":[5.2202797E-1,0E0,0E0],"parents":[2147483647,0,0],"right_children":[2,-1,-1],"split_conditions":[2.3755834E-1,-1.3577233E-3,-8.1749104E-2],"split_indices":[1191,0,0],"split_type":[0,0,0],"sum_hessian":[5.1092496E0,1.0000193E0,4.1092305E0],"tree_param":{"num_deleted":"0","num_feature":"2048","num_nodes":"3","size_leaf_vector":"1"}},{"base_weights":[-6.6946644E-1,-1.3267015E-3,-8.03655E-2],"categories":[],"categories_nodes":[],"categories_segments":[],"categories_sizes":[],"default_left":[0,0,0],"id":25,"left_children":[1,-1,-1],"loss_changes":[4.9961543E-1,0E0,0E0],"parents":[2147483647,0,0],"right_children":[2,-1,-1],"split_conditions":[1.5798487E-1,-1.3267015E-3,-8.03655E-2],"split_indices":[1961,0,0],"split_type":[0,0,0],"sum_hessian":[4.7950277E0,1.0006392E0,3.7943888E0],"tree_param":{"num_deleted":"0","num_feature":"2048","num_nodes":"3","size_leaf_vector":"1"}},{"base_weights":[-6.5073454E-1,-7.8945115E-2,-1.2684348E-3],"categories":[],"categories_nodes":[],"categories_segments":[],"categories_sizes":[],"default_left":[0,0,0],"id":26,"left_children":[1,-1,-1],"loss_changes":[4.7757792E-1,0E0,0E0],"parents":[2147483647,0,0],"right_children":[2,-1,-1],"split_conditions":[5.4058313E-1,-7.8945115E-2,-1.2684348E-3],"split_indices":[1113,0,0],"split_type":[0,0,0],"sum_hessian":[4.5090027E0,3.5088644E0,1.0001384E0],"tree_param":{"num_deleted":"0","num_feature":"2048","num_nodes":"3","size_leaf_vector":"1"}},{"base_weights":[-6.319929E-1,-1.2280849E-3,-7.7498585E-2],"categories":[],"categories_nodes":[],"categories_segments":[],"categories_sizes":[],"default_left":[0,0,0],"id":27,"left_children":[1,-1,-1],"loss_changes":[4.5557165E-1,0E0,0E0],"parents":[2147483647,0,0],"right_children":[2,-1,-1],"split_conditions":[1.9329414E-1,-1.2280849E-3,-7.7498585E-2],"split_indices":[42,0,0],"split_type":[0,0,0],"sum_hessian":[4.248456E0,1.0000895E0,3.2483666E0],"tree_param":{"num_deleted":"0","num_feature":"2048","num_nodes":"3","size_leaf_vector":"1"}},{"base_weights":[-6.1330014E-1,-7.603018E-2,-1.1886345E-3],"categories":[],"categories_nodes":[],"categories_segments":[],"categories_sizes":[],"default_left":[0,0,0],"id":28,"left_children":[1,-1,-1],"loss_changes":[4.3398392E-1,0E0,0E0],"parents":[2147483647,0,0],"right_children":[2,-1,-1],"split_conditions":[4.8709404E-1,-7.603018E-2,-1.1886345E-3],"split_indices":[1707,0,0],"split_type":[0,0,0],"sum_hessian":[4.011057E0,3.0109177E0,1.0001394E0],"tree_param":{"num_deleted":"0","num_feature":"2048","num_nodes":"3","size_leaf_vector":"1"}},{"base_weights":[-5.947142E-1,-1.1614496E-3,-7.453519E-2],"categories":[],"categories_nodes":[],"categories_segments":[],"categories_sizes":[],"default_left":[0,0,0],"id":29,"left_children":[1,-1,-1],"loss_changes":[4.124912E-1,0E0,0E0],"parents":[2147483647,0,0],"right_children":[2,-1,-1],"split_conditions":[2.7813753E-1,-1.1614496E-3,-7.453519E-2],"split_indices":[574,0,0],"split_type":[0,0,0],"sum_hessian":[3.7946634E0,1.0001829E0,2.7944806E0],"tree_param":{"num_deleted":"0","num_feature":"2048","num_nodes":"3","size_leaf_vector":"1"}},{"base_weights":[-5.7629776E-1,-7.3020354E-2,-1.1348473E-3],"categories":[],"categories_nodes":[],"categories_segments":[],"categories_sizes":[],"default_left":[0,0,0],"id":30,"left_children":[1,-1,-1],"loss_changes":[3.9144266E-1,0E0,0E0],"parents":[2147483647,0,0],"right_children":[2,-1,-1],"split_conditions":[6.8121606E-1,-7.3020354E-2,-1.1348473E-3],"split_indices":[1571,0,0],"split_type":[0,0,0],"sum_hessian":[3.5972884E0,2.597229E0,1.0000592E0],"tree_param":{"num_deleted":"0","num_feature":"2048","num_nodes":"3","size_leaf_vector":"1"}},{"base_weights":[-5.5810803E-1,-1.0965682E-3,-7.150292E-2],"categories":[],"categories_nodes":[],"categories_segments":[],"categories_sizes":[],"default_left":[0,0,0],"id":31,"left_children":[1,-1,-1],"loss_changes":[3.7140596E-1,0E0,0E0],"parents":[2147483647,0,0],"right_children":[2,-1,-1],"split_conditions":[3.0464578E-1,-1.0965682E-3,-7.150292E-2],"split_indices":[315,0,0],"split_type":[0,0,0],"sum_hessian":[3.41713E0,1.0000614E0,2.4170685E0],"tree_param":{"num_deleted":"0","num_feature":"2048","num_nodes":"3","size_leaf_vector":"1"}},{"base_weights":[-5.401896E-1,-1.0687105E-3,-6.9970325E-2],"categories":[],"categories_nodes":[],"categories_segments":[],"categories_sizes":[],"default_left":[0,0,0],"id":32,"left_children":[1,-1,-1],"loss_changes":[3.5171092E-1,0E0,0E0],"parents":[2147483647,0,0],"right_children":[2,-1,-1],"split_conditions":[4.0522477E-1,-1.0687105E-3,-6.9970325E-2],"split_indices":[1062,0,0],"split_type":[0,0,0],"sum_hessian":[3.2526236E0,1.0000324E0,2.2525911E0],"tree_param":{"num_deleted":"0","num_feature":"2048","num_nodes":"3","size_leaf_vector":"1"}},{"base_weights":[-5.2259374E-1,-6.842956E-2,-1.048243E-3],"categories":[],"categories_nodes":[],"categories_segments":[],"categories_sizes":[],"default_left":[0,0,0],"id":33,"left_children":[1,-1,-1],"loss_changes":[3.325336E-1,0E0,0E0],"parents":[2147483647,0,0],"right_children":[2,-1,-1],"split_conditions":[6.5226495E-1,-6.842956E-2,-1.048243E-3],"split_indices":[576,0,0],"split_type":[0,0,0],"sum_hessian":[3.1022754E0,2.1022534E0,1.0000218E0],"tree_param":{"num_deleted":"0","num_feature":"2048","num_nodes":"3","size_leaf_vector":"1"}},{"base_weights":[-5.053644E-1,-1.031323E-3,-6.688778E-2],"categories":[],"categories_nodes":[],"categories_segments":[],"categories_sizes":[],"default_left":[0,0,0],"id":34,"left_children":[1,-1,-1],"loss_changes":[3.1403792E-1,0E0,0E0],"parents":[2147483647,0,0],"right_children":[2,-1,-1],"split_conditions":[2.7507702E-1,-1.031323E-3,-6.688778E-2],"split_indices":[1947,0,0],"split_type":[0,0,0],"sum_hessian":[2.9647467E0,1.0000571E0,1.9646897E0],"tree_param":{"num_deleted":"0","num_feature":"2048","num_nodes":"3","size_leaf_vector":"1"}},{"base_weights":[-4.8853827E-1,-6.5353654E-2,-1.0106942E-3],"categories":[],"categories_nodes":[],"categories_segments":[],"categories_sizes":[],"default_left":[0,0,0],"id":35,"left_children":[1,-1,-1],"loss_changes":[2.9643393E-1,0E0,0E0],"parents":[2147483647,0,0],"right_children":[2,-1,-1],"split_conditions":[5.003748E-1,-6.5353654E-2,-1.0106942E-3],"split_indices":[784,0,0],"split_type":[0,0,0],"sum_hessian":[2.838839E0,1.8387163E0,1.0001228E0],"tree_param":{"num_deleted":"0","num_feature":"2048","num_nodes":"3","size_leaf_vector":"1"}},{"base_weights":[-4.7214413E-1,-9.896952E-4,-6.382373E-2],"categories":[],"categories_nodes":[],"categories_segments":[],"categories_sizes":[],"default_left":[0,0,0],"id":36,"left_children":[1,-1,-1],"loss_changes":[2.795576E-1,0E0,0E0],"parents":[2147483647,0,0],"right_children":[2,-1,-1],"split_conditions":[3.799087E-1,-9.896952E-4,-6.382373E-2],"split_indices":[1715,0,0],"split_type":[0,0,0],"sum_hessian":[2.72348E0,1.0000018E0,1.7234781E0],"tree_param":{"num_deleted":"0","num_feature":"2048","num_nodes":"3","size_leaf_vector":"1"}},{"base_weights":[-4.5620948E-1,-9.7467465E-4,-6.2304843E-2],"categories":[],"categories_nodes":[],"categories_segments":[],"categories_sizes":[],"default_left":[0,0,0],"id":37,"left_children":[1,-1,-1],"loss_changes":[2.6339757E-1,0E0,0E0],"parents":[2147483647,0,0],"right_children":[2,-1,-1],"split_conditions":[4.6091112E-1,-9.7467465E-4,-6.2304843E-2],"split_indices":[860,0,0],"split_type":[0,0,0],"sum_hessian":[2.6176624E0,1.0000197E0,1.6176426E0],"tree_param":{"num_deleted":"0","num_feature":"2048","num_nodes":"3","size_leaf_vector":"1"}},{"base_weights":[-4.407541E-1,-6.0800888E-2,-9.605577E-4],"categories":[],"categories_nodes":[],"categories_segments":[],"categories_sizes":[],"default_left":[0,0,0],"id":38,"left_children":[1,-1,-1],"loss_changes":[2.4802935E-1,0E0,0E0],"parents":[2147483647,0,0],"right_children":[2,-1,-1],"split_conditions":[5.038682E-1,-6.0800888E-2,-9.605577E-4],"split_indices":[124,0,0],"split_type":[0,0,0],"sum_hessian":[2.5205073E0,1.5204673E0,1.0000399E0],"tree_param":{"num_deleted":"0","num_feature":"2048","num_nodes":"3","size_leaf_vector":"1"}},{"base_weights":[-4.2579263E-1,-5.9316643E-2,-9.438895E-4],"categories":[],"categories_nodes":[],"categories_segments":[],"categories_sizes":[],"default_left":[0,0,0],"id":39,"left_children":[1,-1,-1],"loss_changes":[2.3351109E-1,0E0,0E0],"parents":[2147483647,0,0],"right_children":[2,-1,-1],"split_conditions":[6.249256E-1,-5.9316643E-2,-9.438895E-4],"split_indices":[139,0,0],"split_type":[0,0,0],"sum_hessian":[2.4312122E0,1.4312013E0,1.0000108E0],"tree_param":{"num_deleted":"0","num_feature":"2048","num_nodes":"3","size_leaf_vector":"1"}},{"base_weights":[-4.1133443E-1,-9.2963845E-4,-5.7852693E-2],"categories":[],"categories_nodes":[],"categories_segments":[],"categories_sizes":[],"default_left":[0,0,0],"id":40,"left_children":[1,-1,-1],"loss_changes":[2.1973747E-1,0E0,0E0],"parents":[2147483647,0,0],"right_children":[2,-1,-1],"split_conditions":[3.561427E-1,-9.2963845E-4,-5.7852693E-2],"split_indices":[221,0,0],"split_type":[0,0,0],"sum_hessian":[2.349052E0,1.0000038E0,1.3490483E0],"tree_param":{"num_deleted":"0","num_feature":"2048","num_nodes":"3","size_leaf_vector":"1"}},{"base_weights":[-3.97385E-1,-9.213239E-4,-5.6409415E-2],"categories":[],"categories_nodes":[],"categories_segments":[],"categories_sizes":[],"default_left":[0,0,0],"id":41,"left_children":[1,-1,-1],"loss_changes":[2.0662838E-1,0E0,0E0],"parents":[2147483647,0,0],"right_children":[2,-1,-1],"split_conditions":[3.60009E-1,-9.213239E-4,-5.6409415E-2],"split_indices":[196,0,0],"split_type":[0,0,0],"sum_hessian":[2.2733705E0,1.0000595E0,1.2733111E0],"tree_param":{"num_deleted":"0","num_feature":"2048","num_nodes":"3","size_leaf_vector":"1"}},{"base_weights":[-3.8394675E-1,-5.4995913E-2,-9.0851105E-4],"categories":[],"categories_nodes":[],"categories_segments":[],"categories_sizes":[],"default_left":[0,0,0],"id":42,"left_children":[1,-1,-1],"loss_changes":[1.9436741E-1,0E0,0E0],"parents":[2147483647,0,0],"right_children":[2,-1,-1],"split_conditions":[4.790116E-1,-5.4995913E-2,-9.0851105E-4],"split_indices":[774,0,0],"split_type":[0,0,0],"sum_hessian":[2.2035747E0,1.2034932E0,1.0000815E0],"tree_param":{"num_deleted":"0","num_feature":"2048","num_nodes":"3","size_leaf_vector":"1"}},{"base_weights":[-3.7101611E-1,-5.3605366E-2,-9.006524E-4],"categories":[],"categories_nodes":[],"categories_segments":[],"categories_sizes":[],"default_left":[0,0,0],"id":43,"left_children":[1,-1,-1],"loss_changes":[1.8272021E-1,0E0,0E0],"parents":[2147483647,0,0],"right_children":[2,-1,-1],"split_conditions":[5.093745E-1,-5.3605366E-2,-9.006524E-4],"split_indices":[1333,0,0],"split_type":[0,0,0],"sum_hessian":[2.1391358E0,1.1390702E0,1.0000658E0],"tree_param":{"num_deleted":"0","num_feature":"2048","num_nodes":"3","size_leaf_vector":"1"}},{"base_weights":[-3.5858917E-1,-5.2247565E-2,-8.8938884E-4],"categories":[],"categories_nodes":[],"categories_segments":[],"categories_sizes":[],"default_left":[0,0,0],"id":44,"left_children":[1,-1,-1],"loss_changes":[1.7184362E-1,0E0,0E0],"parents":[2147483647,0,0],"right_children":[2,-1,-1],"split_conditions":[3.8152516E-1,-5.2247565E-2,-8.8938884E-4],"split_indices":[1691,0,0],"split_type":[0,0,0],"sum_hessian":[2.0795586E0,1.0795387E0,1.0000198E0],"tree_param":{"num_deleted":"0","num_feature":"2048","num_nodes":"3","size_leaf_vector":"1"}},{"base_weights":[-3.4665713E-1,-5.092026E-2,-8.8159164E-4],"categories":[],"categories_nodes":[],"categories_segments":[],"categories_sizes":[],"default_left":[0,0,0],"id":45,"left_children":[1,-1,-1],"loss_changes":[1.615952E-1,0E0,0E0],"parents":[2147483647,0,0],"right_children":[2,-1,-1],"split_conditions":[4.4875047E-1,-5.092026E-2,-8.8159164E-4],"split_indices":[710,0,0],"split_type":[0,0,0],"sum_hessian":[2.024413E0,1.0243455E0,1.0000676E0],"tree_param":{"num_deleted":"0","num_feature":"2048","num_nodes":"3","size_leaf_vector":"1"}},{"base_weights":[-3.3520967E-1],"categories":[],"categories_nodes":[],"categories_segments":[],"categories_sizes":[],"default_left":[0],"id":46,"left_children":[-1],"loss_changes":[0E0],"parents":[2147483647],"right_children":[-1],"split_conditions":[-3.3520967E-2],"split_indices":[0],"split_type":[0],"sum_hessian":[1.9733115E0],"tree_param":{"num_deleted":"0","num_feature":"2048","num_nodes":"1","size_leaf_vector":"1"}},{"base_weights":[-3.201768E-1],"categories":[],"categories_nodes":[],"categories_segments":[],"categories_sizes":[],"default_left":[0],"id":47,"left_children":[-1],"loss_changes":[0E0],"parents":[2147483647],"right_children":[-1],"split_conditions":[-3.201768E-2],"split_indices":[0],"split_type":[0],"sum_hessian":[1.9096658E0],"tree_param":{"num_deleted":"0","num_feature":"2048","num_nodes":"1","size_leaf_vector":"1"}},{"base_weights":[-3.056776E-1],"categories":[],"categories_nodes":[],"categories_segments":[],"categories_sizes":[],"default_left":[0],"id":48,"left_children":[-1],"loss_changes":[0E0],"parents":[2147483647],"right_children":[-1],"split_conditions":[-3.056776E-2],"split_indices":[0],"split_type":[0],"sum_hessian":[1.8507563E0],"tree_param":{"num_deleted":"0","num_feature":"2048","num_nodes":"1","size_leaf_vector":"1"}},{"base_weights":[-2.917113E-1],"categories":[],"categories_nodes":[],"categories_segments":[],"categories_sizes":[],"default_left":[0],"id":49,"left_children":[-1],"loss_changes":[0E0],"parents":[2147483647],"right_children":[-1],"split_conditions":[-2.917113E-2],"split_indices":[0],"split_type":[0],"sum_hessian":[1.79618E0],"tree_param":{"num_deleted":"0","num_feature":"2048","num_nodes":"1","size_leaf_vector":"1"}},{"base_weights":[-2.7827445E-1],"categories":[],"categories_nodes":[],"categories_segments":[],"categories_sizes":[],"default_left":[0],"id":50,"left_children":[-1],"loss_changes":[0E0],"parents":[2147483647],"right_children":[-1],"split_conditions":[-2.7827445E-2],"split_indices":[0],"split_type":[0],"sum_hessian":[1.7455719E0],"tree_param":{"num_deleted":"0","num_feature":"2048","num_nodes":"1","size_leaf_vector":"1"}},{"base_weights":[-2.6536137E-1],"categories":[],"categories_nodes":[],"categories_segments":[],"categories_sizes":[],"default_left":[0],"id":51,"left_children":[-1],"loss_changes":[0E0],"parents":[2147483647],"right_children":[-1],"split_conditions":[-2.6536137E-2],"split_indices":[0],"split_type":[0],"sum_hessian":[1.6986011E0],"tree_param":{"num_deleted":"0","num_feature":"2048","num_nodes":"1","size_leaf_vector":"1"}},{"base_weights":[-2.5296423E-1],"categories":[],"categories_nodes":[],"categories_segments":[],"categories_sizes":[],"default_left":[0],"id":52,"left_children":[-1],"loss_changes":[0E0],"parents":[2147483647],"right_children":[-1],"split_conditions":[-2.5296424E-2],"split_indices":[0],"split_type":[0],"sum_hessian":[1.6549674E0],"tree_param":{"num_deleted":"0","num_feature":"2048","num_nodes":"1","size_leaf_vector":"1"}},{"base_weights":[-2.4107361E-1],"categories":[],"categories_nodes":[],"categories_segments":[],"categories_sizes":[],"default_left":[0],"id":53,"left_children":[-1],"loss_changes":[0E0],"parents":[2147483647],"right_children":[-1],"split_conditions":[-2.4107361E-2],"split_indices":[0],"split_type":[0],"sum_hessian":[1.6143987E0],"tree_param":{"num_deleted":"0","num_feature":"2048","num_nodes":"1","size_leaf_vector":"1"}},{"base_weights":[-2.2967845E-1],"categories":[],"categories_nodes":[],"categories_segments":[],"categories_sizes":[],"default_left":[0],"id":54,"left_children":[-1],"loss_changes":[0E0],"parents":[2147483647],"right_children":[-1],"split_conditions":[-2.2967845E-2],"split_indices":[0],"split_type":[0],"sum_hessian":[1.5766469E0],"tree_param":{"num_deleted":"0","num_feature":"2048","num_nodes":"1","size_leaf_vector":"1"}},{"base_weights":[-2.187669E-1],"categories":[],"categories_nodes":[],"categories_segments":[],"categories_sizes":[],"default_left":[0],"id":55,"left_children":[-1],"loss_changes":[0E0],"parents":[2147483647],"right_children":[-1],"split_conditions":[-2.187669E-2],"split_indices":[0],"split_type":[0],"sum_hessian":[1.5414879E0],"tree_param":{"num_deleted":"0","num_feature":"2048","num_nodes":"1","size_leaf_vector":"1"}},{"base_weights":[-2.0832576E-1],"categories":[],"categories_nodes":[],"categories_segments":[],"categories_sizes":[],"default_left":[0],"id":56,"left_children":[-1],"loss_changes":[0E0],"parents":[2147483647],"right_children":[-1],"split_conditions":[-2.0832576E-2],"split_indices":[0],"split_type":[0],"sum_hessian":[1.5087168E0],"tree_param":{"num_deleted":"0","num_feature":"2048","num_nodes":"1","size_leaf_vector":"1"}},{"base_weights":[-1.9834147E-1],"categories":[],"categories_nodes":[],"categories_segments":[],"categories_sizes":[],"default_left":[0],"id":57,"left_children":[-1],"loss_changes":[0E0],"parents":[2147483647],"right_children":[-1],"split_conditions":[-1.9834148E-2],"split_indices":[0],"split_type":[0],"sum_hessian":[1.4781476E0],"tree_param":{"num_deleted":"0","num_feature":"2048","num_nodes":"1","size_leaf_vector":"1"}},{"base_weights":[-1.887997E-1],"categories":[],"categories_nodes":[],"categories_segments":[],"categories_sizes":[],"default_left":[0],"id":58,"left_children":[-1],"loss_changes":[0E0],"parents":[2147483647],"right_children":[-1],"split_conditions":[-1.887997E-2],"split_indices":[0],"split_type":[0],"sum_hessian":[1.4496104E0],"tree_param":{"num_deleted":"0","num_feature":"2048","num_nodes":"1","size_leaf_vector":"1"}},{"base_weights":[-1.7968576E-1],"categories":[],"categories_nodes":[],"categories_segments":[],"categories_sizes":[],"default_left":[0],"id":59,"left_children":[-1],"loss_changes":[0E0],"parents":[2147483647],"right_children":[-1],"split_conditions":[-1.7968576E-2],"split_indices":[0],"split_type":[0],"sum_hessian":[1.4229501E0],"tree_param":{"num_deleted":"0","num_feature":"2048","num_nodes":"1","size_leaf_vector":"1"}},{"base_weights":[-1.7098473E-1],"categories":[],"categories_nodes":[],"categories_segments":[],"categories_sizes":[],"default_left":[0],"id":60,"left_children":[-1],"loss_changes":[0E0],"parents":[2147483647],"right_children":[-1],"split_conditions":[-1.7098473E-2],"split_indices":[0],"split_type":[0],"sum_hessian":[1.3980254E0],"tree_param":{"num_deleted":"0","num_feature":"2048","num_nodes":"1","size_leaf_vector":"1"}},{"base_weights":[-1.6268176E-1],"categories":[],"categories_nodes":[],"categories_segments":[],"categories_sizes":[],"default_left":[0],"id":61,"left_children":[-1],"loss_changes":[0E0],"parents":[2147483647],"right_children":[-1],"split_conditions":[-1.6268177E-2],"split_indices":[0],"split_type":[0],"sum_hessian":[1.3747072E0],"tree_param":{"num_deleted":"0","num_feature":"2048","num_nodes":"1","size_leaf_vector":"1"}},{"base_weights":[-1.5476182E-1],"categories":[],"categories_nodes":[],"categories_segments":[],"categories_sizes":[],"default_left":[0],"id":62,"left_children":[-1],"loss_changes":[0E0],"parents":[2147483647],"right_children":[-1],"split_conditions":[-1.5476182E-2],"split_indices":[0],"split_type":[0],"sum_hessian":[1.3528771E0],"tree_param":{"num_deleted":"0","num_feature":"2048","num_nodes":"1","size_leaf_vector":"1"}},{"base_weights":[-1.4721008E-1],"categories":[],"categories_nodes":[],"categories_segments":[],"categories_sizes":[],"default_left":[0],"id":63,"left_children":[-1],"loss_changes":[0E0],"parents":[2147483647],"right_children":[-1],"split_conditions":[-1.4721008E-2],"split_indices":[0],"split_type":[0],"sum_hessian":[1.332427E0],"tree_param":{"num_deleted":"0","num_feature":"2048","num_nodes":"1","size_leaf_vector":"1"}},{"base_weights":[-1.400119E-1],"categories":[],"categories_nodes":[],"categories_segments":[],"categories_sizes":[],"default_left":[0],"id":64,"left_children":[-1],"loss_changes":[0E0],"parents":[2147483647],"right_children":[-1],"split_conditions":[-1.4001191E-2],"split_indices":[0],"split_type":[0],"sum_hessian":[1.3132578E0],"tree_param":{"num_deleted":"0","num_feature":"2048","num_nodes":"1","size_leaf_vector":"1"}},{"base_weights":[-1.3315268E-1],"categories":[],"categories_nodes":[],"categories_segments":[],"categories_sizes":[],"default_left":[0],"id":65,"left_children":[-1],"loss_changes":[0E0],"parents":[2147483647],"right_children":[-1],"split_conditions":[-1.3315268E-2],"split_indices":[0],"split_type":[0],"sum_hessian":[1.295278E0],"tree_param":{"num_deleted":"0","num_feature":"2048","num_nodes":"1","size_leaf_vector":"1"}},{"base_weights":[-1.2661849E-1],"categories":[],"categories_nodes":[],"categories_segments":[],"categories_sizes":[],"default_left":[0],"id":66,"left_children":[-1],"loss_changes":[0E0],"parents":[2147483647],"right_children":[-1],"split_conditions":[-1.2661849E-2],"split_indices":[0],"split_type":[0],"sum_hessian":[1.2784045E0],"tree_param":{"num_deleted":"0","num_feature":"2048","num_nodes":"1","size_leaf_vector":"1"}},{"base_weights":[-1.2039529E-1],"categories":[],"categories_nodes":[],"categories_segments":[],"categories_sizes":[],"default_left":[0],"id":67,"left_children":[-1],"loss_changes":[0E0],"parents":[2147483647],"right_children":[-1],"split_conditions":[-1.2039529E-2],"split_indices":[0],"split_type":[0],"sum_hessian":[1.2625599E0],"tree_param":{"num_deleted":"0","num_feature":"2048","num_nodes":"1","size_leaf_vector":"1"}},{"base_weights":[-1.144697E-1],"categories":[],"categories_nodes":[],"categories_segments":[],"categories_sizes":[],"default_left":[0],"id":68,"left_children":[-1],"loss_changes":[0E0],"parents":[2147483647],"right_children":[-1],"split_conditions":[-1.14469705E-2],"split_indices":[0],"split_type":[0],"sum_hessian":[1.2476737E0],"tree_param":{"num_deleted":"0","num_feature":"2048","num_nodes":"1","size_leaf_vector":"1"}},{"base_weights":[-1.0882875E-1],"categories":[],"categories_nodes":[],"categories_segments":[],"categories_sizes":[],"default_left":[0],"id":69,"left_children":[-1],"loss_changes":[0E0],"parents":[2147483647],"right_children":[-1],"split_conditions":[-1.0882876E-2],"split_indices":[0],"split_type":[0],"sum_hessian":[1.233681E0],"tree_param":{"num_deleted":"0","num_feature":"2048","num_nodes":"1","size_leaf_vector":"1"}},{"base_weights":[-1.0345971E-1],"categories":[],"categories_nodes":[],"categories_segments":[],"categories_sizes":[],"default_left":[0],"id":70,"left_children":[-1],"loss_changes":[0E0],"parents":[2147483647],"right_children":[-1],"split_conditions":[-1.0345971E-2],"split_indices":[0],"split_type":[0],"sum_hessian":[1.2205213E0],"tree_param":{"num_deleted":"0","num_feature":"2048","num_nodes":"1","size_leaf_vector":"1"}},{"base_weights":[-9.835032E-2],"categories":[],"categories_nodes":[],"categories_segments":[],"categories_sizes":[],"default_left":[0],"id":71,"left_children":[-1],"loss_changes":[0E0],"parents":[2147483647],"right_children":[-1],"split_conditions":[-9.835032E-3],"split_indices":[0],"split_type":[0],"sum_hessian":[1.2081394E0],"tree_param":{"num_deleted":"0","num_feature":"2048","num_nodes":"1","size_leaf_vector":"1"}},{"base_weights":[-9.348863E-2],"categories":[],"categories_nodes":[],"categories_segments":[],"categories_sizes":[],"default_left":[0],"id":72,"left_children":[-1],"loss_changes":[0E0],"parents":[2147483647],"right_children":[-1],"split_conditions":[-9.348864E-3],"split_indices":[0],"split_type":[0],"sum_hessian":[1.1964837E0],"tree_param":{"num_deleted":"0","num_feature":"2048","num_nodes":"1","size_leaf_vector":"1"}},{"base_weights":[-8.886354E-2],"categories":[],"categories_nodes":[],"categories_segments":[],"categories_sizes":[],"default_left":[0],"id":73,"left_children":[-1],"loss_changes":[0E0],"parents":[2147483647],"right_children":[-1],"split_conditions":[-8.886354E-3],"split_indices":[0],"split_type":[0],"sum_hessian":[1.1855072E0],"tree_param":{"num_deleted":"0","num_feature":"2048","num_nodes":"1","size_leaf_vector":"1"}},{"base_weights":[-8.4463954E-2],"categories":[],"categories_nodes":[],"categories_segments":[],"categories_sizes":[],"default_left":[0],"id":74,"left_children":[-1],"loss_changes":[0E0],"parents":[2147483647],"right_children":[-1],"split_conditions":[-8.446395E-3],"split_indices":[0],"split_type":[0],"sum_hessian":[1.175166E0],"tree_param":{"num_deleted":"0","num_feature":"2048","num_nodes":"1","size_leaf_vector":"1"}},{"base_weights":[-8.0279425E-2],"categories":[],"categories_nodes":[],"categories_segments":[],"categories_sizes":[],"default_left":[0],"id":75,"left_children":[-1],"loss_changes":[0E0],"parents":[2147483647],"right_children":[-1],"split_conditions":[-8.027943E-3],"split_indices":[0],"split_type":[0],"sum_hessian":[1.1654195E0],"tree_param":{"num_deleted":"0","num_feature":"2048","num_nodes":"1","size_leaf_vector":"1"}},{"base_weights":[-7.629962E-2],"categories":[],"categories_nodes":[],"categories_segments":[],"categories_sizes":[],"default_left":[0],"id":76,"left_children":[-1],"loss_changes":[0E0],"parents":[2147483647],"right_children":[-1],"split_conditions":[-7.629962E-3],"split_indices":[0],"split_type":[0],"sum_hessian":[1.1562294E0],"tree_param":{"num_deleted":"0","num_feature":"2048","num_nodes":"1","size_leaf_vector":"1"}},{"base_weights":[-7.251513E-2],"categories":[],"categories_nodes":[],"categories_segments":[],"categories_sizes":[],"default_left":[0],"id":77,"left_children":[-1],"loss_changes":[0E0],"parents":[2147483647],"right_children":[-1],"split_conditions":[-7.251513E-3],"split_indices":[0],"split_type":[0],"sum_hessian":[1.1475616E0],"tree_param":{"num_deleted":"0","num_feature":"2048","num_nodes":"1","size_leaf_vector":"1"}},{"base_weights":[-6.891643E-2],"categories":[],"categories_nodes":[],"categories_segments":[],"categories_sizes":[],"default_left":[0],"id":78,"left_children":[-1],"loss_changes":[0E0],"parents":[2147483647],"right_children":[-1],"split_conditions":[-6.891643E-3],"split_indices":[0],"split_type":[0],"sum_hessian":[1.1393827E0],"tree_param":{"num_deleted":"0","num_feature":"2048","num_nodes":"1","size_leaf_vector":"1"}},{"base_weights":[-6.549483E-2],"categories":[],"categories_nodes":[],"categories_segments":[],"categories_sizes":[],"default_left":[0],"id":79,"left_children":[-1],"loss_changes":[0E0],"parents":[2147483647],"right_children":[-1],"split_conditions":[-6.5494827E-3],"split_indices":[0],"split_type":[0],"sum_hessian":[1.1316633E0],"tree_param":{"num_deleted":"0","num_feature":"2048","num_nodes":"1","size_leaf_vector":"1"}},{"base_weights":[-6.2241916E-2],"categories":[],"categories_nodes":[],"categories_segments":[],"categories_sizes":[],"default_left":[0],"id":80,"left_children":[-1],"loss_changes":[0E0],"parents":[2147483647],"right_children":[-1],"split_conditions":[-6.2241917E-3],"split_indices":[0],"split_type":[0],"sum_hessian":[1.1243752E0],"tree_param":{"num_deleted":"0","num_feature":"2048","num_nodes":"1","size_leaf_vector":"1"}},{"base_weights":[-5.9149373E-2],"categories":[],"categories_nodes":[],"categories_segments":[],"categories_sizes":[],"default_left":[0],"id":81,"left_children":[-1],"loss_changes":[0E0],"parents":[2147483647],"right_children":[-1],"split_conditions":[-5.9149372E-3],"split_indices":[0],"split_type":[0],"sum_hessian":[1.117492E0],"tree_param":{"num_deleted":"0","num_feature":"2048","num_nodes":"1","size_leaf_vector":"1"}},{"base_weights":[-5.6209404E-2],"categories":[],"categories_nodes":[],"categories_segments":[],"categories_sizes":[],"default_left":[0],"id":82,"left_children":[-1],"loss_changes":[0E0],"parents":[2147483647],"right_children":[-1],"split_conditions":[-5.6209406E-3],"split_indices":[0],"split_type":[0],"sum_hessian":[1.110989E0],"tree_param":{"num_deleted":"0","num_feature":"2048","num_nodes":"1","size_leaf_vector":"1"}},{"base_weights":[-5.341484E-2],"categories":[],"categories_nodes":[],"categories_segments":[],"categories_sizes":[],"default_left":[0],"id":83,"left_children":[-1],"loss_changes":[0E0],"parents":[2147483647],"right_children":[-1],"split_conditions":[-5.341484E-3],"split_indices":[0],"split_type":[0],"sum_hessian":[1.1048441E0],"tree_param":{"num_deleted":"0","num_feature":"2048","num_nodes":"1","size_leaf_vector":"1"}},{"base_weights":[-5.0758474E-2],"categories":[],"categories_nodes":[],"categories_segments":[],"categories_sizes":[],"default_left":[0],"id":84,"left_children":[-1],"loss_changes":[0E0],"parents":[2147483647],"right_children":[-1],"split_conditions":[-5.0758473E-3],"split_indices":[0],"split_type":[0],"sum_hessian":[1.0990359E0],"tree_param":{"num_deleted":"0","num_feature":"2048","num_nodes":"1","size_leaf_vector":"1"}},{"base_weights":[-4.8233613E-2],"categories":[],"categories_nodes":[],"categories_segments":[],"categories_sizes":[],"default_left":[0],"id":85,"left_children":[-1],"loss_changes":[0E0],"parents":[2147483647],"right_children":[-1],"split_conditions":[-4.8233615E-3],"split_indices":[0],"split_type":[0],"sum_hessian":[1.0935442E0],"tree_param":{"num_deleted":"0","num_feature":"2048","num_nodes":"1","size_leaf_vector":"1"}},{"base_weights":[-4.58339E-2],"categories":[],"categories_nodes":[],"categories_segments":[],"categories_sizes":[],"default_left":[0],"id":86,"left_children":[-1],"loss_changes":[0E0],"parents":[2147483647],"right_children":[-1],"split_conditions":[-4.58339E-3],"split_indices":[0],"split_type":[0],"sum_hessian":[1.0883512E0],"tree_param":{"num_deleted":"0","num_feature":"2048","num_nodes":"1","size_leaf_vector":"1"}},{"base_weights":[-4.3553118E-2],"categories":[],"categories_nodes":[],"categories_segments":[],"categories_sizes":[],"default_left":[0],"id":87,"left_children":[-1],"loss_changes":[0E0],"parents":[2147483647],"right_children":[-1],"split_conditions":[-4.355312E-3],"split_indices":[0],"split_type":[0],"sum_hessian":[1.0834391E0],"tree_param":{"num_deleted":"0","num_feature":"2048","num_nodes":"1","size_leaf_vector":"1"}},{"base_weights":[-4.1385375E-2],"categories":[],"categories_nodes":[],"categories_segments":[],"categories_sizes":[],"default_left":[0],"id":88,"left_children":[-1],"loss_changes":[0E0],"parents":[2147483647],"right_children":[-1],"split_conditions":[-4.1385377E-3],"split_indices":[0],"split_type":[0],"sum_hessian":[1.0787914E0],"tree_param":{"num_deleted":"0","num_feature":"2048","num_nodes":"1","size_leaf_vector":"1"}},{"base_weights":[-3.932528E-2],"categories":[],"categories_nodes":[],"categories_segments":[],"categories_sizes":[],"default_left":[0],"id":89,"left_children":[-1],"loss_changes":[0E0],"parents":[2147483647],"right_children":[-1],"split_conditions":[-3.9325277E-3],"split_indices":[0],"split_type":[0],"sum_hessian":[1.0743936E0],"tree_param":{"num_deleted":"0","num_feature":"2048","num_nodes":"1","size_leaf_vector":"1"}},{"base_weights":[-3.7367456E-2],"categories":[],"categories_nodes":[],"categories_segments":[],"categories_sizes":[],"default_left":[0],"id":90,"left_children":[-1],"loss_changes":[0E0],"parents":[2147483647],"right_children":[-1],"split_conditions":[-3.7367456E-3],"split_indices":[0],"split_type":[0],"sum_hessian":[1.0702311E0],"tree_param":{"num_deleted":"0","num_feature":"2048","num_nodes":"1","size_leaf_vector":"1"}},{"base_weights":[-3.550675E-2],"categories":[],"categories_nodes":[],"categories_segments":[],"categories_sizes":[],"default_left":[0],"id":91,"left_children":[-1],"loss_changes":[0E0],"parents":[2147483647],"right_children":[-1],"split_conditions":[-3.5506752E-3],"split_indices":[0],"split_type":[0],"sum_hessian":[1.0662903E0],"tree_param":{"num_deleted":"0","num_feature":"2048","num_nodes":"1","size_leaf_vector":"1"}},{"base_weights":[-3.373863E-2],"categories":[],"categories_nodes":[],"categories_segments":[],"categories_sizes":[],"default_left":[0],"id":92,"left_children":[-1],"loss_changes":[0E0],"parents":[2147483647],"right_children":[-1],"split_conditions":[-3.3738632E-3],"split_indices":[0],"split_type":[0],"sum_hessian":[1.0625594E0],"tree_param":{"num_deleted":"0","num_feature":"2048","num_nodes":"1","size_leaf_vector":"1"}},{"base_weights":[-3.205825E-2],"categories":[],"categories_nodes":[],"categories_segments":[],"categories_sizes":[],"default_left":[0],"id":93,"left_children":[-1],"loss_changes":[0E0],"parents":[2147483647],"right_children":[-1],"split_conditions":[-3.205825E-3],"split_indices":[0],"split_type":[0],"sum_hessian":[1.0590258E0],"tree_param":{"num_deleted":"0","num_feature":"2048","num_nodes":"1","size_leaf_vector":"1"}},{"base_weights":[-3.0461527E-2],"categories":[],"categories_nodes":[],"categories_segments":[],"categories_sizes":[],"default_left":[0],"id":94,"left_children":[-1],"loss_changes":[0E0],"parents":[2147483647],"right_children":[-1],"split_conditions":[-3.0461529E-3],"split_indices":[0],"split_type":[0],"sum_hessian":[1.0556792E0],"tree_param":{"num_deleted":"0","num_feature":"2048","num_nodes":"1","size_leaf_vector":"1"}},{"base_weights":[-2.8944233E-2],"categories":[],"categories_nodes":[],"categories_segments":[],"categories_sizes":[],"default_left":[0],"id":95,"left_children":[-1],"loss_changes":[0E0],"parents":[2147483647],"right_children":[-1],"split_conditions":[-2.8944234E-3],"split_indices":[0],"split_type":[0],"sum_hessian":[1.0525091E0],"tree_param":{"num_deleted":"0","num_feature":"2048","num_nodes":"1","size_leaf_vector":"1"}},{"base_weights":[-2.7502364E-2],"categories":[],"categories_nodes":[],"categories_segments":[],"categories_sizes":[],"default_left":[0],"id":96,"left_children":[-1],"loss_changes":[0E0],"parents":[2147483647],"right_children":[-1],"split_conditions":[-2.7502363E-3],"split_indices":[0],"split_type":[0],"sum_hessian":[1.0495055E0],"tree_param":{"num_deleted":"0","num_feature":"2048","num_nodes":"1","size_leaf_vector":"1"}},{"base_weights":[-2.6132172E-2],"categories":[],"categories_nodes":[],"categories_segments":[],"categories_sizes":[],"default_left":[0],"id":97,"left_children":[-1],"loss_changes":[0E0],"parents":[2147483647],"right_children":[-1],"split_conditions":[-2.6132173E-3],"split_indices":[0],"split_type":[0],"sum_hessian":[1.0466592E0],"tree_param":{"num_deleted":"0","num_feature":"2048","num_nodes":"1","size_leaf_vector":"1"}},{"base_weights":[-2.4830278E-2],"categories":[],"categories_nodes":[],"categories_segments":[],"categories_sizes":[],"default_left":[0],"id":98,"left_children":[-1],"loss_changes":[0E0],"parents":[2147483647],"right_children":[-1],"split_conditions":[-2.4830278E-3],"split_indices":[0],"split_type":[0],"sum_hessian":[1.0439621E0],"tree_param":{"num_deleted":"0","num_feature":"2048","num_nodes":"1","size_leaf_vector":"1"}},{"base_weights":[-2.3593185E-2],"categories":[],"categories_nodes":[],"categories_segments":[],"categories_sizes":[],"default_left":[0],"id":99,"left_children":[-1],"loss_changes":[0E0],"parents":[2147483647],"right_children":[-1],"split_conditions":[-2.3593185E-3],"split_indices":[0],"split_type":[0],"sum_hessian":[1.0414057E0],"tree_param":{"num_deleted":"0","num_feature":"2048","num_nodes":"1","size_leaf_vector":"1"}}]},"name":"gbtree"},"learner_model_param":{"base_score":"1.205216E-1","boost_from_average":"1","num_class":"0","num_feature":"2048","num_target":"1"},"objective":{"name":"binary:logistic","reg_loss_param":{"scale_pos_weight":"1"}}},"version":[2,0,1]}