{"learner":{"attributes":{"scikit_learn":"{\"_estimator_type\": \"classifier\"}"},"feature_names":[],"feature_types":[],"gradient_booster":{"model":{"gbtree_model_param":{"num_parallel_tree":"1","num_trees":"100"},"iteration_indptr":[0,1,2,3,4,5,6,7,8,9,10,11,12,13,14,15,16,17,18,19,20,21,22,23,24,25,26,27,28,29,30,31,32,33,34,35,36,37,38,39,40,41,42,43,44,45,46,47,48,49,50,51,52,53,54,55,56,57,58,59,60,61,62,63,64,65,66,67,68,69,70,71,72,73,74,75,76,77,78,79,80,81,82,83,84,85,86,87,88,89,90,91,92,93,94,95,96,97,98,99,100],"tree_info":[0,0,0,0,0,0,0,0,0,0,0,0,0,0,0,0,0,0,0,0,0,0,0,0,0,0,0,0,0,0,0,0,0,0,0,0,0,0,0,0,0,0,0,0,0,0,0,0,0,0,0,0,0,0,0,0,0,0,0,0,0,0,0,0,0,0,0,0,0,0,0,0,0,0,0,0,0,0,0,0,0,0,0,0,0,0,0,0,0,0,0,0,0,0,0,0,0,0,0,0],"trees":[{"base_weights":[-1.049697E0,-1.10543646E-1,3.7751377E-2],"categories":[],"categories_nodes":[],"categories_segments":[],"categories_sizes":[],"default_left":[0,0,0],"id":0,"left_children":[1,-1,-1],"loss_changes":[3.2208443E0,0E0,0E0],"parents":[2147483647,0,0],"right_children":[2,-1,-1],"split_conditions":[1.2214507E0,-1.10543646E-1,3.7751377E-2],"split_indices":[466,0,0],"split_type":[0,0,0],"sum_hessian":[3.4241516E1,3.317147E1,1.0700474E0],"tree_param":{"num_deleted":"0","num_feature":"2048","num_nodes":"3","size_leaf_vector":"1"}},{"base_weights":[-1.028996E0,4.2043384E-2,-1.08909644E-1],"categories":[],"categories_nodes":[],"categories_segments":[],"categories_sizes":[],"default_left":[0,0,0],"id":1,"left_children":[1,-1,-1],"loss_changes":[3.2953758E0,0E0,0E0],"parents":[2147483647,0,0],"right_children":[2,-1,-1],"split_conditions":[1.0879188E-1,4.2043384E-2,-1.08909644E-1],"split_indices":[1672,0,0],"split_type":[0,0,0],"sum_hessian":[3.157307E1,1.0183427E0,3.0554728E1],"tree_param":{"num_deleted":"0","num_feature":"2048","num_nodes":"3","size_leaf_vector":"1"}},{"base_weights":[-1.0093099E0,-1.07419506E-1,4.102326E-2],"categories":[],"categories_nodes":[],"categories_segments":[],"categories_sizes":[],"default_left":[0,0,0],"id":2,"left_children":[1,-1,-1],"loss_changes":[3.2123203E0,0E0,0E0],"parents":[2147483647,0,0],"right_children":[2,-1,-1],"split_conditions":[1.1309229E0,-1.07419506E-1,4.102326E-2],"split_indices":[1815,0,0],"split_type":[0,0,0],"sum_hessian":[2.909153E1,2.8052568E1,1.0389615E0],"tree_param":{"num_deleted":"0","num_feature":"2048","num_nodes":"3","size_leaf_vector":"1"}},{"base_weights":[-9.9038845E-1,-1.0598308E-1,3.8263112E-2],"categories":[],"categories_nodes":[],"categories_segments":[],"categories_sizes":[],"default_left":[0,0,0],"id":3,"left_children":[1,-1,-1],"loss_changes":[3.0556812E0,0E0,0E0],"parents":[2147483647,0,0],"right_children":[2,-1,-1],"split_conditions":[1.1309229E0,-1.0598308E-1,3.8263112E-2],"split_indices":[1815,0,0],"split_type":[0,0,0],"sum_hessian":[2.6795235E1,2.5722391E1,1.0728437E0],"tree_param":{"num_deleted":"0","num_feature":"2048","num_nodes":"3","size_leaf_vector":"1"}},{"base_weights":[-9.7216016E-1,-1.0470849E-1,4.1455917E-2],"categories":[],"categories_nodes":[],"categories_segments":[],"categories_sizes":[],"default_left":[0,0,0],"id":4,"left_children":[1,-1,-1],"loss_changes":[3.101572E0,0E0,0E0],"parents":[2147483647,0,0],"right_children":[2,-1,-1],"split_conditions":[1.1649114E0,-1.0470849E-1,4.1455917E-2],"split_indices":[466,0,0],"split_type":[0,0,0],"sum_hessian":[2.4673763E1,2.3641336E1,1.0324271E0],"tree_param":{"num_deleted":"0","num_feature":"2048","num_nodes":"3","size_leaf_vector":"1"}},{"base_weights":[-9.543038E-1,-1.0356333E-1,4.247592E-2],"categories":[],"categories_nodes":[],"categories_segments":[],"categories_sizes":[],"default_left":[0,0,0],"id":5,"left_children":[1,-1,-1],"loss_changes":[3.0998783E0,0E0,0E0],"parents":[2147483647,0,0],"right_children":[2,-1,-1],"split_conditions":[6.658651E-1,-1.0356333E-1,4.247592E-2],"split_indices":[1931,0,0],"split_type":[0,0,0],"sum_hessian":[2.271628E1,2.1686369E1,1.0299106E0],"tree_param":{"num_deleted":"0","num_feature":"2048","num_nodes":"3","size_leaf_vector":"1"}},{"base_weights":[-9.365427E-1,-1.02399044E-1,4.3491144E-2],"categories":[],"categories_nodes":[],"categories_segments":[],"categories_sizes":[],"default_left":[0,0,0],"id":6,"left_children":[1,-1,-1],"loss_changes":[3.0739956E0,0E0,0E0],"parents":[2147483647,0,0],"right_children":[2,-1,-1],"split_conditions":[7.646325E-1,-1.02399044E-1,4.3491144E-2],"split_indices":[450,0,0],"split_type":[0,0,0],"sum_hessian":[2.0918112E1,1.9902431E1,1.0156802E0],"tree_param":{"num_deleted":"0","num_feature":"2048","num_nodes":"3","size_leaf_vector":"1"}},{"base_weights":[-9.189127E-1,4.3779586E-2,-1.0134212E-1],"categories":[],"categories_nodes":[],"categories_segments":[],"categories_sizes":[],"default_left":[0,0,0],"id":7,"left_children":[1,-1,-1],"loss_changes":[3.0420609E0,0E0,0E0],"parents":[2147483647,0,0],"right_children":[2,-1,-1],"split_conditions":[1.2090219E-1,4.3779586E-2,-1.0134212E-1],"split_indices":[608,0,0],"split_type":[0,0,0],"sum_hessian":[1.926501E1,1.0180551E0,1.8246956E1],"tree_param":{"num_deleted":"0","num_feature":"2048","num_nodes":"3","size_leaf_vector":"1"}},{"base_weights":[-9.01173E-1,4.4998076E-2,-1.0026715E-1],"categories":[],"categories_nodes":[],"categories_segments":[],"categories_sizes":[],"default_left":[0,0,0],"id":8,"left_children":[1,-1,-1],"loss_changes":[3.0226507E0,0E0,0E0],"parents":[2147483647,0,0],"right_children":[2,-1,-1],"split_conditions":[1.2605482E-1,4.4998076E-2,-1.0026715E-1],"split_indices":[1759,0,0],"split_type":[0,0,0],"sum_hessian":[1.7750666E1,1.0003663E0,1.67503E1],"tree_param":{"num_deleted":"0","num_feature":"2048","num_nodes":"3","size_leaf_vector":"1"}},{"base_weights":[-8.8334405E-1,4.4505138E-2,-9.921947E-2],"categories":[],"categories_nodes":[],"categories_segments":[],"categories_sizes":[],"default_left":[0,0,0],"id":9,"left_children":[1,-1,-1],"loss_changes":[2.9520273E0,0E0,0E0],"parents":[2147483647,0,0],"right_children":[2,-1,-1],"split_conditions":[1.2090219E-1,4.4505138E-2,-9.921947E-2],"split_indices":[608,0,0],"split_type":[0,0,0],"sum_hessian":[1.6361732E1,1.0052451E0,1.5356487E1],"tree_param":{"num_deleted":"0","num_feature":"2048","num_nodes":"3","size_leaf_vector":"1"}},{"base_weights":[-8.6534905E-1,-9.8237194E-2,4.3231945E-2],"categories":[],"categories_nodes":[],"categories_segments":[],"categories_sizes":[],"default_left":[0,0,0],"id":10,"left_children":[1,-1,-1],"loss_changes":[2.8681755E0,0E0,0E0],"parents":[2147483647,0,0],"right_children":[2,-1,-1],"split_conditions":[1.0336827E0,-9.8237194E-2,4.3231945E-2],"split_indices":[1080,0,0],"split_type":[0,0,0],"sum_hessian":[1.5090656E1,1.4065234E1,1.0254219E0],"tree_param":{"num_deleted":"0","num_feature":"2048","num_nodes":"3","size_leaf_vector":"1"}},{"base_weights":[-8.4702104E-1,4.4451647E-2,-9.725439E-2],"categories":[],"categories_nodes":[],"categories_segments":[],"categories_sizes":[],"default_left":[0,0,0],"id":11,"left_children":[1,-1,-1],"loss_changes":[2.852913E0,0E0,0E0],"parents":[2147483647,0,0],"right_children":[2,-1,-1],"split_conditions":[1.769284E-1,4.4451647E-2,-9.725439E-2],"split_indices":[1955,0,0],"split_type":[0,0,0],"sum_hessian":[1.3931158E1,1.0089092E0,1.2922249E1],"tree_param":{"num_deleted":"0","num_feature":"2048","num_nodes":"3","size_leaf_vector":"1"}},{"base_weights":[-8.283402E-1,4.4548515E-2,-9.62585E-2],"categories":[],"categories_nodes":[],"categories_segments":[],"categories_sizes":[],"default_left":[0,0,0],"id":12,"left_children":[1,-1,-1],"loss_changes":[2.800846E0,0E0,0E0],"parents":[2147483647,0,0],"right_children":[2,-1,-1],"split_conditions":[1.3000979E-1,4.4548515E-2,-9.62585E-2],"split_indices":[1979,0,0],"split_type":[0,0,0],"sum_hessian":[1.2871164E1,1.0060909E0,1.1865074E1],"tree_param":{"num_deleted":"0","num_feature":"2048","num_nodes":"3","size_leaf_vector":"1"}},{"base_weights":[-8.0930007E-1,-9.52496E-2,4.4624664E-2],"categories":[],"categories_nodes":[],"categories_segments":[],"categories_sizes":[],"default_left":[0,0,0],"id":13,"left_children":[1,-1,-1],"loss_changes":[2.7449217E0,0E0,0E0],"parents":[2147483647,0,0],"right_children":[2,-1,-1],"split_conditions":[8.7149715E-1,-9.52496E-2,4.4624664E-2],"split_indices":[1094,0,0],"split_type":[0,0,0],"sum_hessian":[1.1903293E1,1.0901355E1,1.0019373E0],"tree_param":{"num_deleted":"0","num_feature":"2048","num_nodes":"3","size_leaf_vector":"1"}},{"base_weights":[-7.8990287E-1,4.418383E-2,-9.425884E-2],"categories":[],"categories_nodes":[],"categories_segments":[],"categories_sizes":[],"default_left":[0,0,0],"id":14,"left_children":[1,-1,-1],"loss_changes":[2.6769762E0,0E0,0E0],"parents":[2147483647,0,0],"right_children":[2,-1,-1],"split_conditions":[1.4192903E-1,4.418383E-2,-9.425884E-2],"split_indices":[1685,0,0],"split_type":[0,0,0],"sum_hessian":[1.1019557E1,1.0064621E0,1.0013095E1],"tree_param":{"num_deleted":"0","num_feature":"2048","num_nodes":"3","size_leaf_vector":"1"}},{"base_weights":[-7.7009046E-1,-9.3225986E-2,4.40997E-2],"categories":[],"categories_nodes":[],"categories_segments":[],"categories_sizes":[],"default_left":[0,0,0],"id":15,"left_children":[1,-1,-1],"loss_changes":[2.613617E0,0E0,0E0],"parents":[2147483647,0,0],"right_children":[2,-1,-1],"split_conditions":[9.931134E-1,-9.3225986E-2,4.40997E-2],"split_indices":[466,0,0],"split_type":[0,0,0],"sum_hessian":[1.0214247E1,9.211076E0,1.0031704E0],"tree_param":{"num_deleted":"0","num_feature":"2048","num_nodes":"3","size_leaf_vector":"1"}},{"base_weights":[-7.4992794E-1,-9.225078E-2,4.4134274E-2],"categories":[],"categories_nodes":[],"categories_segments":[],"categories_sizes":[],"default_left":[0,0,0],"id":16,"left_children":[1,-1,-1],"loss_changes":[2.561583E0,0E0,0E0],"parents":[2147483647,0,0],"right_children":[2,-1,-1],"split_conditions":[7.476587E-1,-9.225078E-2,4.4134274E-2],"split_indices":[188,0,0],"split_type":[0,0,0],"sum_hessian":[9.479347E0,8.476905E0,1.0024424E0],"tree_param":{"num_deleted":"0","num_feature":"2048","num_nodes":"3","size_leaf_vector":"1"}},{"base_weights":[-7.293048E-1,4.3993033E-2,-9.119901E-2],"categories":[],"categories_nodes":[],"categories_segments":[],"categories_sizes":[],"default_left":[0,0,0],"id":17,"left_children":[1,-1,-1],"loss_changes":[2.4967375E0,0E0,0E0],"parents":[2147483647,0,0],"right_children":[2,-1,-1],"split_conditions":[1.8465918E-1,4.3993033E-2,-9.119901E-2],"split_indices":[1955,0,0],"split_type":[0,0,0],"sum_hessian":[8.810413E0,1.0002723E0,7.810141E0],"tree_param":{"num_deleted":"0","num_feature":"2048","num_nodes":"3","size_leaf_vector":"1"}},{"base_weights":[-7.0834816E-1,4.372081E-2,-9.0139665E-2],"categories":[],"categories_nodes":[],"categories_segments":[],"categories_sizes":[],"default_left":[0,0,0],"id":18,"left_children":[1,-1,-1],"loss_changes":[2.4287663E0,0E0,0E0],"parents":[2147483647,0,0],"right_children":[2,-1,-1],"split_conditions":[2.0787473E-1,4.372081E-2,-9.0139665E-2],"split_indices":[768,0,0],"split_type":[0,0,0],"sum_hessian":[8.20049E0,1.0002447E0,7.200246E0],"tree_param":{"num_deleted":"0","num_feature":"2048","num_nodes":"3","size_leaf_vector":"1"}},{"base_weights":[-6.870763E-1,4.3395914E-2,-8.9067295E-2],"categories":[],"categories_nodes":[],"categories_segments":[],"categories_sizes":[],"default_left":[0,0,0],"id":19,"left_children":[1,-1,-1],"loss_changes":[2.3595948E0,0E0,0E0],"parents":[2147483647,0,0],"right_children":[2,-1,-1],"split_conditions":[1.9182152E-1,4.3395914E-2,-8.9067295E-2],"split_indices":[1780,0,0],"split_type":[0,0,0],"sum_hessian":[7.644791E0,1.0011016E0,6.643689E0],"tree_param":{"num_deleted":"0","num_feature":"2048","num_nodes":"3","size_leaf_vector":"1"}},{"base_weights":[-6.6552526E-1,-8.797885E-2,4.303301E-2],"categories":[],"categories_nodes":[],"categories_segments":[],"categories_sizes":[],"default_left":[0,0,0],"id":20,"left_children":[1,-1,-1],"loss_changes":[2.2895803E0,0E0,0E0],"parents":[2147483647,0,0],"right_children":[2,-1,-1],"split_conditions":[6.507054E-1,-8.797885E-2,4.303301E-2],"split_indices":[627,0,0],"split_type":[0,0,0],"sum_hessian":[7.1387095E0,6.136132E0,1.0025778E0],"tree_param":{"num_deleted":"0","num_feature":"2048","num_nodes":"3","size_leaf_vector":"1"}},{"base_weights":[-6.4374256E-1,4.2753108E-2,-8.684398E-2],"categories":[],"categories_nodes":[],"categories_segments":[],"categories_sizes":[],"default_left":[0,0,0],"id":21,"left_children":[1,-1,-1],"loss_changes":[2.2194645E0,0E0,0E0],"parents":[2147483647,0,0],"right_children":[2,-1,-1],"split_conditions":[1.7730628E-1,4.2753108E-2,-8.684398E-2],"split_indices":[136,0,0],"split_type":[0,0,0],"sum_hessian":[6.677962E0,1.0013235E0,5.6766386E0],"tree_param":{"num_deleted":"0","num_feature":"2048","num_nodes":"3","size_leaf_vector":"1"}},{"base_weights":[-6.218294E-1,-8.568735E-2,4.238619E-2],"categories":[],"categories_nodes":[],"categories_segments":[],"categories_sizes":[],"default_left":[0,0,0],"id":22,"left_children":[1,-1,-1],"loss_changes":[2.1470604E0,0E0,0E0],"parents":[2147483647,0,0],"right_children":[2,-1,-1],"split_conditions":[7.2150743E-1,-8.568735E-2,4.238619E-2],"split_indices":[518,0,0],"split_type":[0,0,0],"sum_hessian":[6.2578673E0,5.2568355E0,1.0010319E0],"tree_param":{"num_deleted":"0","num_feature":"2048","num_nodes":"3","size_leaf_vector":"1"}},{"base_weights":[-5.998548E-1,-8.451332E-2,4.204381E-2],"categories":[],"categories_nodes":[],"categories_segments":[],"categories_sizes":[],"default_left":[0,0,0],"id":23,"left_children":[1,-1,-1],"loss_changes":[2.0757961E0,0E0,0E0],"parents":[2147483647,0,0],"right_children":[2,-1,-1],"split_conditions":[7.0749116E-1,-8.451332E-2,4.204381E-2],"split_indices":[1996,0,0],"split_type":[0,0,0],"sum_hessian":[5.874845E0,4.8746543E0,1.0001909E0],"tree_param":{"num_deleted":"0","num_feature":"2048","num_nodes":"3","size_leaf_vector":"1"}},{"base_weights":[-5.778884E-1,-8.332034E-2,4.1623823E-2],"categories":[],"categories_nodes":[],"categories_segments":[],"categories_sizes":[],"default_left":[0,0,0],"id":24,"left_children":[1,-1,-1],"loss_changes":[2.003085E0,0E0,0E0],"parents":[2147483647,0,0],"right_children":[2,-1,-1],"split_conditions":[7.5621355E-1,-8.332034E-2,4.1623823E-2],"split_indices":[1133,0,0],"split_type":[0,0,0],"sum_hessian":[5.5255065E0,4.5252028E0,1.0003036E0],"tree_param":{"num_deleted":"0","num_feature":"2048","num_nodes":"3","size_leaf_vector":"1"}},{"base_weights":[-5.560041E-1,-8.211015E-2,4.1193213E-2],"categories":[],"categories_nodes":[],"categories_segments":[],"categories_sizes":[],"default_left":[0,0,0],"id":25,"left_children":[1,-1,-1],"loss_changes":[1.9309096E0,0E0,0E0],"parents":[2147483647,0,0],"right_children":[2,-1,-1],"split_conditions":[6.6335773E-1,-8.211015E-2,4.1193213E-2],"split_indices":[1000,0,0],"split_type":[0,0,0],"sum_hessian":[5.20689E0,4.2065134E0,1.0003767E0],"tree_param":{"num_deleted":"0","num_feature":"2048","num_nodes":"3","size_leaf_vector":"1"}},{"base_weights":[-5.342776E-1,-8.085989E-2,4.0671542E-2],"categories":[],"categories_nodes":[],"categories_segments":[],"categories_sizes":[],"default_left":[0,0,0],"id":26,"left_children":[1,-1,-1],"loss_changes":[1.8560416E0,0E0,0E0],"parents":[2147483647,0,0],"right_children":[2,-1,-1],"split_conditions":[6.590423E-1,-8.085989E-2,4.0671542E-2],"split_indices":[1534,0,0],"split_type":[0,0,0],"sum_hessian":[4.916187E0,3.915441E0,1.0007459E0],"tree_param":{"num_deleted":"0","num_feature":"2048","num_nodes":"3","size_leaf_vector":"1"}},{"base_weights":[-5.128101E-1,-7.961372E-2,4.020849E-2],"categories":[],"categories_nodes":[],"categories_segments":[],"categories_sizes":[],"default_left":[0,0,0],"id":27,"left_children":[1,-1,-1],"loss_changes":[1.7848448E0,0E0,0E0],"parents":[2147483647,0,0],"right_children":[2,-1,-1],"split_conditions":[7.691164E-1,-7.961372E-2,4.020849E-2],"split_indices":[120,0,0],"split_type":[0,0,0],"sum_hessian":[4.6506476E0,3.6500847E0,1.0005628E0],"tree_param":{"num_deleted":"0","num_feature":"2048","num_nodes":"3","size_leaf_vector":"1"}},{"base_weights":[-4.9165577E-1,3.9767526E-2,-7.836502E-2],"categories":[],"categories_nodes":[],"categories_segments":[],"categories_sizes":[],"default_left":[0,0,0],"id":28,"left_children":[1,-1,-1],"loss_changes":[1.7159992E0,0E0,0E0],"parents":[2147483647,0,0],"right_children":[2,-1,-1],"split_conditions":[1.7888719E-1,3.9767526E-2,-7.836502E-2],"split_indices":[363,0,0],"split_type":[0,0,0],"sum_hessian":[4.4080524E0,1.0001019E0,3.4079506E0],"tree_param":{"num_deleted":"0","num_feature":"2048","num_nodes":"3","size_leaf_vector":"1"}},{"base_weights":[-4.7087553E-1,3.9188143E-2,-7.706915E-2],"categories":[],"categories_nodes":[],"categories_segments":[],"categories_sizes":[],"default_left":[0,0,0],"id":29,"left_children":[1,-1,-1],"loss_changes":[1.643558E0,0E0,0E0],"parents":[2147483647,0,0],"right_children":[2,-1,-1],"split_conditions":[1.7602554E-1,3.9188143E-2,-7.706915E-2],"split_indices":[363,0,0],"split_type":[0,0,0],"sum_hessian":[4.186327E0,1.0004207E0,3.1859062E0],"tree_param":{"num_deleted":"0","num_feature":"2048","num_nodes":"3","size_leaf_vector":"1"}},{"base_weights":[-4.505678E-1,-7.578604E-2,3.866898E-2],"categories":[],"categories_nodes":[],"categories_segments":[],"categories_sizes":[],"default_left":[0,0,0],"id":30,"left_children":[1,-1,-1],"loss_changes":[1.5751858E0,0E0,0E0],"parents":[2147483647,0,0],"right_children":[2,-1,-1],"split_conditions":[4.6511412E-1,-7.578604E-2,3.866898E-2],"split_indices":[481,0,0],"split_type":[0,0,0],"sum_hessian":[3.9833403E0,2.98325E0,1.0000905E0],"tree_param":{"num_deleted":"0","num_feature":"2048","num_nodes":"3","size_leaf_vector":"1"}},{"base_weights":[-4.307738E-1,3.8123827E-2,-7.450687E-2],"categories":[],"categories_nodes":[],"categories_segments":[],"categories_sizes":[],"default_left":[0,0,0],"id":31,"left_children":[1,-1,-1],"loss_changes":[1.5084059E0,0E0,0E0],"parents":[2147483647,0,0],"right_children":[2,-1,-1],"split_conditions":[2.2288719E-1,3.8123827E-2,-7.450687E-2],"split_indices":[1909,0,0],"split_type":[0,0,0],"sum_hessian":[3.7974274E0,1.0002325E0,2.797195E0],"tree_param":{"num_deleted":"0","num_feature":"2048","num_nodes":"3","size_leaf_vector":"1"}},{"base_weights":[-4.1153914E-1,-7.319607E-2,3.7524506E-2],"categories":[],"categories_nodes":[],"categories_segments":[],"categories_sizes":[],"default_left":[0,0,0],"id":32,"left_children":[1,-1,-1],"loss_changes":[1.4411732E0,0E0,0E0],"parents":[2147483647,0,0],"right_children":[2,-1,-1],"split_conditions":[6.905296E-1,-7.319607E-2,3.7524506E-2],"split_indices":[335,0,0],"split_type":[0,0,0],"sum_hessian":[3.627118E0,2.626958E0,1.0001602E0],"tree_param":{"num_deleted":"0","num_feature":"2048","num_nodes":"3","size_leaf_vector":"1"}},{"base_weights":[-3.929307E-1,3.6974683E-2,-7.192224E-2],"categories":[],"categories_nodes":[],"categories_segments":[],"categories_sizes":[],"default_left":[0,0,0],"id":33,"left_children":[1,-1,-1],"loss_changes":[1.3785005E0,0E0,0E0],"parents":[2147483647,0,0],"right_children":[2,-1,-1],"split_conditions":[2.4058819E-1,3.6974683E-2,-7.192224E-2],"split_indices":[1098,0,0],"split_type":[0,0,0],"sum_hessian":[3.4707506E0,1.0000484E0,2.470702E0],"tree_param":{"num_deleted":"0","num_feature":"2048","num_nodes":"3","size_leaf_vector":"1"}},{"base_weights":[-3.7496048E-1,3.6345173E-2,-7.061526E-2],"categories":[],"categories_nodes":[],"categories_segments":[],"categories_sizes":[],"default_left":[0,0,0],"id":34,"left_children":[1,-1,-1],"loss_changes":[1.3149078E0,0E0,0E0],"parents":[2147483647,0,0],"right_children":[2,-1,-1],"split_conditions":[5.3886604E-1,3.6345173E-2,-7.061526E-2],"split_indices":[1556,0,0],"split_type":[0,0,0],"sum_hessian":[3.3272462E0,1.0000877E0,2.3271585E0],"tree_param":{"num_deleted":"0","num_feature":"2048","num_nodes":"3","size_leaf_vector":"1"}},{"base_weights":[-3.5768232E-1,3.5746526E-2,-6.934337E-2],"categories":[],"categories_nodes":[],"categories_segments":[],"categories_sizes":[],"default_left":[0,0,0],"id":35,"left_children":[1,-1,-1],"loss_changes":[1.2552019E0,0E0,0E0],"parents":[2147483647,0,0],"right_children":[2,-1,-1],"split_conditions":[3.4226176E-1,3.5746526E-2,-6.934337E-2],"split_indices":[912,0,0],"split_type":[0,0,0],"sum_hessian":[3.1952274E0,1.00018E0,2.1950474E0],"tree_param":{"num_deleted":"0","num_feature":"2048","num_nodes":"3","size_leaf_vector":"1"}},{"base_weights":[-3.41101E-1,-6.80613E-2,3.511731E-2],"categories":[],"categories_nodes":[],"categories_segments":[],"categories_sizes":[],"default_left":[0,0,0],"id":36,"left_children":[1,-1,-1],"loss_changes":[1.1964998E0,0E0,0E0],"parents":[2147483647,0,0],"right_children":[2,-1,-1],"split_conditions":[5.441083E-1,-6.80613E-2,3.511731E-2],"split_indices":[1487,0,0],"split_type":[0,0,0],"sum_hessian":[3.0737996E0,2.0736597E0,1.0001402E0],"tree_param":{"num_deleted":"0","num_feature":"2048","num_nodes":"3","size_leaf_vector":"1"}},{"base_weights":[-3.2524222E-1,3.449096E-2,-6.679789E-2],"categories":[],"categories_nodes":[],"categories_segments":[],"categories_sizes":[],"default_left":[0,0,0],"id":37,"left_children":[1,-1,-1],"loss_changes":[1.1403791E0,0E0,0E0],"parents":[2147483647,0,0],"right_children":[2,-1,-1],"split_conditions":[2.9716563E-1,3.449096E-2,-6.679789E-2],"split_indices":[62,0,0],"split_type":[0,0,0],"sum_hessian":[2.9618797E0,1.0000821E0,1.9617975E0],"tree_param":{"num_deleted":"0","num_feature":"2048","num_nodes":"3","size_leaf_vector":"1"}},{"base_weights":[-3.1011042E-1,3.3852E-2,-6.554962E-2],"categories":[],"categories_nodes":[],"categories_segments":[],"categories_sizes":[],"default_left":[0,0,0],"id":38,"left_children":[1,-1,-1],"loss_changes":[1.0863397E0,0E0,0E0],"parents":[2147483647,0,0],"right_children":[2,-1,-1],"split_conditions":[2.9148594E-1,3.3852E-2,-6.554962E-2],"split_indices":[1046,0,0],"split_type":[0,0,0],"sum_hessian":[2.8586354E0,1.0001825E0,1.8584528E0],"tree_param":{"num_deleted":"0","num_feature":"2048","num_nodes":"3","size_leaf_vector":"1"}},{"base_weights":[-2.957071E-1,-6.4311035E-2,3.3209275E-2],"categories":[],"categories_nodes":[],"categories_segments":[],"categories_sizes":[],"default_left":[0,0,0],"id":39,"left_children":[1,-1,-1],"loss_changes":[1.0343485E0,0E0,0E0],"parents":[2147483647,0,0],"right_children":[2,-1,-1],"split_conditions":[6.6217464E-1,-6.4311035E-2,3.3209275E-2],"split_indices":[1313,0,0],"split_type":[0,0,0],"sum_hessian":[2.7633078E0,1.7632163E0,1.0000917E0],"tree_param":{"num_deleted":"0","num_feature":"2048","num_nodes":"3","size_leaf_vector":"1"}},{"base_weights":[-2.820312E-1,-6.308748E-2,3.254511E-2],"categories":[],"categories_nodes":[],"categories_segments":[],"categories_sizes":[],"default_left":[0,0,0],"id":40,"left_children":[1,-1,-1],"loss_changes":[9.8414004E-1,0E0,0E0],"parents":[2147483647,0,0],"right_children":[2,-1,-1],"split_conditions":[3.568236E-1,-6.308748E-2,3.254511E-2],"split_indices":[1112,0,0],"split_type":[0,0,0],"sum_hessian":[2.675136E0,1.6748532E0,1.0002829E0],"tree_param":{"num_deleted":"0","num_feature":"2048","num_nodes":"3","size_leaf_vector":"1"}},{"base_weights":[-2.690757E-1,-6.1888702E-2,3.190593E-2],"categories":[],"categories_nodes":[],"categories_segments":[],"categories_sizes":[],"default_left":[0,0,0],"id":41,"left_children":[1,-1,-1],"loss_changes":[9.367769E-1,0E0,0E0],"parents":[2147483647,0,0],"right_children":[2,-1,-1],"split_conditions":[5.707585E-1,-6.1888702E-2,3.190593E-2],"split_indices":[1665,0,0],"split_type":[0,0,0],"sum_hessian":[2.5935094E0,1.5934619E0,1.0000476E0],"tree_param":{"num_deleted":"0","num_feature":"2048","num_nodes":"3","size_leaf_vector":"1"}},{"base_weights":[-2.5682437E-1,-6.0701437E-2,3.1240541E-2],"categories":[],"categories_nodes":[],"categories_segments":[],"categories_sizes":[],"default_left":[0,0,0],"id":42,"left_children":[1,-1,-1],"loss_changes":[8.9087105E-1,0E0,0E0],"parents":[2147483647,0,0],"right_children":[2,-1,-1],"split_conditions":[8.272187E-1,-6.0701437E-2,3.1240541E-2],"split_indices":[170,0,0],"split_type":[0,0,0],"sum_hessian":[2.5178163E0,1.5177306E0,1.0000857E0],"tree_param":{"num_deleted":"0","num_feature":"2048","num_nodes":"3","size_leaf_vector":"1"}},{"base_weights":[-2.4526465E-1,-5.9538033E-2,3.057901E-2],"categories":[],"categories_nodes":[],"categories_segments":[],"categories_sizes":[],"default_left":[0,0,0],"id":43,"left_children":[1,-1,-1],"loss_changes":[8.4720516E-1,0E0,0E0],"parents":[2147483647,0,0],"right_children":[2,-1,-1],"split_conditions":[5.2053136E-1,-5.9538033E-2,3.057901E-2],"split_indices":[610,0,0],"split_type":[0,0,0],"sum_hessian":[2.4475396E0,1.447454E0,1.0000855E0],"tree_param":{"num_deleted":"0","num_feature":"2048","num_nodes":"3","size_leaf_vector":"1"}},{"base_weights":[-2.3437597E-1,2.9918954E-2,-5.8394875E-2],"categories":[],"categories_nodes":[],"categories_segments":[],"categories_sizes":[],"default_left":[0,0,0],"id":44,"left_children":[1,-1,-1],"loss_changes":[8.0556166E-1,0E0,0E0],"parents":[2147483647,0,0],"right_children":[2,-1,-1],"split_conditions":[4.852118E-1,2.9918954E-2,-5.8394875E-2],"split_indices":[1131,0,0],"split_type":[0,0,0],"sum_hessian":[2.3822134E0,1.000002E0,1.3822113E0],"tree_param":{"num_deleted":"0","num_feature":"2048","num_nodes":"3","size_leaf_vector":"1"}},{"base_weights":[-2.2413658E-1,2.9258305E-2,-5.7279505E-2],"categories":[],"categories_nodes":[],"categories_segments":[],"categories_sizes":[],"default_left":[0,0,0],"id":45,"left_children":[1,-1,-1],"loss_changes":[7.659682E-1,0E0,0E0],"parents":[2147483647,0,0],"right_children":[2,-1,-1],"split_conditions":[3.1091598E-1,2.9258305E-2,-5.7279505E-2],"split_indices":[404,0,0],"split_type":[0,0,0],"sum_hessian":[2.3213944E0,1.0000823E0,1.3213122E0],"tree_param":{"num_deleted":"0","num_feature":"2048","num_nodes":"3","size_leaf_vector":"1"}},{"base_weights":[-2.1452194E-1,2.8609214E-2,-5.6189448E-2],"categories":[],"categories_nodes":[],"categories_segments":[],"categories_sizes":[],"default_left":[0,0,0],"id":46,"left_children":[1,-1,-1],"loss_changes":[7.284899E-1,0E0,0E0],"parents":[2147483647,0,0],"right_children":[2,-1,-1],"split_conditions":[2.5914037E-1,2.8609214E-2,-5.6189448E-2],"split_indices":[1902,0,0],"split_type":[0,0,0],"sum_hessian":[2.2647367E0,1.0000012E0,1.2647353E0],"tree_param":{"num_deleted":"0","num_feature":"2048","num_nodes":"3","size_leaf_vector":"1"}},{"base_weights":[-2.0550586E-1,-5.510519E-2,2.7939534E-2],"categories":[],"categories_nodes":[],"categories_segments":[],"categories_sizes":[],"default_left":[0,0,0],"id":47,"left_children":[1,-1,-1],"loss_changes":[6.9212914E-1,0E0,0E0],"parents":[2147483647,0,0],"right_children":[2,-1,-1],"split_conditions":[4.259403E-1,-5.510519E-2,2.7939534E-2],"split_indices":[1931,0,0],"split_type":[0,0,0],"sum_hessian":[2.2118742E0,1.2118647E0,1.0000095E0],"tree_param":{"num_deleted":"0","num_feature":"2048","num_nodes":"3","size_leaf_vector":"1"}},{"base_weights":[-1.9706632E-1,2.7289672E-2,-5.4064024E-2],"categories":[],"categories_nodes":[],"categories_segments":[],"categories_sizes":[],"default_left":[0,0,0],"id":48,"left_children":[1,-1,-1],"loss_changes":[6.581702E-1,0E0,0E0],"parents":[2147483647,0,0],"right_children":[2,-1,-1],"split_conditions":[2.4326259E-1,2.7289672E-2,-5.4064024E-2],"split_indices":[872,0,0],"split_type":[0,0,0],"sum_hessian":[2.162449E0,1.0001245E0,1.1623244E0],"tree_param":{"num_deleted":"0","num_feature":"2048","num_nodes":"3","size_leaf_vector":"1"}},{"base_weights":[-1.8917318E-1,-5.3041525E-2,2.664482E-2],"categories":[],"categories_nodes":[],"categories_segments":[],"categories_sizes":[],"default_left":[0,0,0],"id":49,"left_children":[1,-1,-1],"loss_changes":[6.2583363E-1,0E0,0E0],"parents":[2147483647,0,0],"right_children":[2,-1,-1],"split_conditions":[6.7647785E-1,-5.3041525E-2,2.664482E-2],"split_indices":[434,0,0],"split_type":[0,0,0],"sum_hessian":[2.116248E0,1.1161435E0,1.0001043E0],"tree_param":{"num_deleted":"0","num_feature":"2048","num_nodes":"3","size_leaf_vector":"1"}},{"base_weights":[-1.8179949E-1,-5.203724E-2,2.6001384E-2],"categories":[],"categories_nodes":[],"categories_segments":[],"categories_sizes":[],"default_left":[0,0,0],"id":50,"left_children":[1,-1,-1],"loss_changes":[5.9497803E-1,0E0,0E0],"parents":[2147483647,0,0],"right_children":[2,-1,-1],"split_conditions":[5.2095634E-1,-5.203724E-2,2.6001384E-2],"split_indices":[1916,0,0],"split_type":[0,0,0],"sum_hessian":[2.0729742E0,1.0729413E0,1.000033E0],"tree_param":{"num_deleted":"0","num_feature":"2048","num_nodes":"3","size_leaf_vector":"1"}},{"base_weights":[-1.7491905E-1,-5.1061608E-2,2.5363995E-2],"categories":[],"categories_nodes":[],"categories_segments":[],"categories_sizes":[],"default_left":[0,0,0],"id":51,"left_children":[1,-1,-1],"loss_changes":[5.6576777E-1,0E0,0E0],"parents":[2147483647,0,0],"right_children":[2,-1,-1],"split_conditions":[4.772581E-1,-5.1061608E-2,2.5363995E-2],"split_indices":[650,0,0],"split_type":[0,0,0],"sum_hessian":[2.0323718E0,1.0322903E0,1.0000814E0],"tree_param":{"num_deleted":"0","num_feature":"2048","num_nodes":"3","size_leaf_vector":"1"}},{"base_weights":[-1.6850479E-1],"categories":[],"categories_nodes":[],"categories_segments":[],"categories_sizes":[],"default_left":[0],"id":52,"left_children":[-1],"loss_changes":[0E0],"parents":[2147483647],"right_children":[-1],"split_conditions":[-1.6850479E-2],"split_indices":[0],"split_type":[0],"sum_hessian":[1.9942553E0],"tree_param":{"num_deleted":"0","num_feature":"2048","num_nodes":"1","size_leaf_vector":"1"}},{"base_weights":[-1.5866224E-1],"categories":[],"categories_nodes":[],"categories_segments":[],"categories_sizes":[],"default_left":[0],"id":53,"left_children":[-1],"loss_changes":[0E0],"parents":[2147483647],"right_children":[-1],"split_conditions":[-1.5866226E-2],"split_indices":[0],"split_type":[0],"sum_hessian":[1.9695227E0],"tree_param":{"num_deleted":"0","num_feature":"2048","num_nodes":"1","size_leaf_vector":"1"}},{"base_weights":[-1.493565E-1],"categories":[],"categories_nodes":[],"categories_segments":[],"categories_sizes":[],"default_left":[0],"id":54,"left_children":[-1],"loss_changes":[0E0],"parents":[2147483647],"right_children":[-1],"split_conditions":[-1.493565E-2],"split_indices":[0],"split_type":[0],"sum_hessian":[1.9465399E0],"tree_param":{"num_deleted":"0","num_feature":"2048","num_nodes":"1","size_leaf_vector":"1"}},{"base_weights":[-1.4056343E-1],"categories":[],"categories_nodes":[],"categories_segments":[],"categories_sizes":[],"default_left":[0],"id":55,"left_children":[-1],"loss_changes":[0E0],"parents":[2147483647],"right_children":[-1],"split_conditions":[-1.4056343E-2],"split_indices":[0],"split_type":[0],"sum_hessian":[1.9251711E0],"tree_param":{"num_deleted":"0","num_feature":"2048","num_nodes":"1","size_leaf_vector":"1"}},{"base_weights":[-1.3225913E-1],"categories":[],"categories_nodes":[],"categories_segments":[],"categories_sizes":[],"default_left":[0],"id":56,"left_children":[-1],"loss_changes":[0E0],"parents":[2147483647],"right_children":[-1],"split_conditions":[-1.3225913E-2],"split_indices":[0],"split_type":[0],"sum_hessian":[1.9052918E0],"tree_param":{"num_deleted":"0","num_feature":"2048","num_nodes":"1","size_leaf_vector":"1"}},{"base_weights":[-1.2442011E-1],"categories":[],"categories_nodes":[],"categories_segments":[],"categories_sizes":[],"default_left":[0],"id":57,"left_children":[-1],"loss_changes":[0E0],"parents":[2147483647],"right_children":[-1],"split_conditions":[-1.244201E-2],"split_indices":[0],"split_type":[0],"sum_hessian":[1.886788E0],"tree_param":{"num_deleted":"0","num_feature":"2048","num_nodes":"1","size_leaf_vector":"1"}},{"base_weights":[-1.17023766E-1],"categories":[],"categories_nodes":[],"categories_segments":[],"categories_sizes":[],"default_left":[0],"id":58,"left_children":[-1],"loss_changes":[0E0],"parents":[2147483647],"right_children":[-1],"split_conditions":[-1.1702376E-2],"split_indices":[0],"split_type":[0],"sum_hessian":[1.8695567E0],"tree_param":{"num_deleted":"0","num_feature":"2048","num_nodes":"1","size_leaf_vector":"1"}},{"base_weights":[-1.1004791E-1],"categories":[],"categories_nodes":[],"categories_segments":[],"categories_sizes":[],"default_left":[0],"id":59,"left_children":[-1],"loss_changes":[0E0],"parents":[2147483647],"right_children":[-1],"split_conditions":[-1.1004791E-2],"split_indices":[0],"split_type":[0],"sum_hessian":[1.8535028E0],"tree_param":{"num_deleted":"0","num_feature":"2048","num_nodes":"1","size_leaf_vector":"1"}},{"base_weights":[-1.0347112E-1],"categories":[],"categories_nodes":[],"categories_segments":[],"categories_sizes":[],"default_left":[0],"id":60,"left_children":[-1],"loss_changes":[0E0],"parents":[2147483647],"right_children":[-1],"split_conditions":[-1.0347112E-2],"split_indices":[0],"split_type":[0],"sum_hessian":[1.8385395E0],"tree_param":{"num_deleted":"0","num_feature":"2048","num_nodes":"1","size_leaf_vector":"1"}},{"base_weights":[-9.727292E-2],"categories":[],"categories_nodes":[],"categories_segments":[],"categories_sizes":[],"default_left":[0],"id":61,"left_children":[-1],"loss_changes":[0E0],"parents":[2147483647],"right_children":[-1],"split_conditions":[-9.727292E-3],"split_indices":[0],"split_type":[0],"sum_hessian":[1.8245877E0],"tree_param":{"num_deleted":"0","num_feature":"2048","num_nodes":"1","size_leaf_vector":"1"}},{"base_weights":[-9.143305E-2],"categories":[],"categories_nodes":[],"categories_segments":[],"categories_sizes":[],"default_left":[0],"id":62,"left_children":[-1],"loss_changes":[0E0],"parents":[2147483647],"right_children":[-1],"split_conditions":[-9.143305E-3],"split_indices":[0],"split_type":[0],"sum_hessian":[1.8115731E0],"tree_param":{"num_deleted":"0","num_feature":"2048","num_nodes":"1","size_leaf_vector":"1"}},{"base_weights":[-8.593267E-2],"categories":[],"categories_nodes":[],"categories_segments":[],"categories_sizes":[],"default_left":[0],"id":63,"left_children":[-1],"loss_changes":[0E0],"parents":[2147483647],"right_children":[-1],"split_conditions":[-8.593268E-3],"split_indices":[0],"split_type":[0],"sum_hessian":[1.7994292E0],"tree_param":{"num_deleted":"0","num_feature":"2048","num_nodes":"1","size_leaf_vector":"1"}},{"base_weights":[-8.075355E-2],"categories":[],"categories_nodes":[],"categories_segments":[],"categories_sizes":[],"default_left":[0],"id":64,"left_children":[-1],"loss_changes":[0E0],"parents":[2147483647],"right_children":[-1],"split_conditions":[-8.075356E-3],"split_indices":[0],"split_type":[0],"sum_hessian":[1.7880939E0],"tree_param":{"num_deleted":"0","num_feature":"2048","num_nodes":"1","size_leaf_vector":"1"}},{"base_weights":[-7.587797E-2],"categories":[],"categories_nodes":[],"categories_segments":[],"categories_sizes":[],"default_left":[0],"id":65,"left_children":[-1],"loss_changes":[0E0],"parents":[2147483647],"right_children":[-1],"split_conditions":[-7.5877975E-3],"split_indices":[0],"split_type":[0],"sum_hessian":[1.7775098E0],"tree_param":{"num_deleted":"0","num_feature":"2048","num_nodes":"1","size_leaf_vector":"1"}},{"base_weights":[-7.128927E-2],"categories":[],"categories_nodes":[],"categories_segments":[],"categories_sizes":[],"default_left":[0],"id":66,"left_children":[-1],"loss_changes":[0E0],"parents":[2147483647],"right_children":[-1],"split_conditions":[-7.1289274E-3],"split_indices":[0],"split_type":[0],"sum_hessian":[1.7676241E0],"tree_param":{"num_deleted":"0","num_feature":"2048","num_nodes":"1","size_leaf_vector":"1"}},{"base_weights":[-6.697166E-2],"categories":[],"categories_nodes":[],"categories_segments":[],"categories_sizes":[],"default_left":[0],"id":67,"left_children":[-1],"loss_changes":[0E0],"parents":[2147483647],"right_children":[-1],"split_conditions":[-6.6971662E-3],"split_indices":[0],"split_type":[0],"sum_hessian":[1.7583889E0],"tree_param":{"num_deleted":"0","num_feature":"2048","num_nodes":"1","size_leaf_vector":"1"}},{"base_weights":[-6.290969E-2],"categories":[],"categories_nodes":[],"categories_segments":[],"categories_sizes":[],"default_left":[0],"id":68,"left_children":[-1],"loss_changes":[0E0],"parents":[2147483647],"right_children":[-1],"split_conditions":[-6.2909694E-3],"split_indices":[0],"split_type":[0],"sum_hessian":[1.7497585E0],"tree_param":{"num_deleted":"0","num_feature":"2048","num_nodes":"1","size_leaf_vector":"1"}},{"base_weights":[-5.9089202E-2],"categories":[],"categories_nodes":[],"categories_segments":[],"categories_sizes":[],"default_left":[0],"id":69,"left_children":[-1],"loss_changes":[0E0],"parents":[2147483647],"right_children":[-1],"split_conditions":[-5.9089204E-3],"split_indices":[0],"split_type":[0],"sum_hessian":[1.7416915E0],"tree_param":{"num_deleted":"0","num_feature":"2048","num_nodes":"1","size_leaf_vector":"1"}},{"base_weights":[-5.5496242E-2],"categories":[],"categories_nodes":[],"categories_segments":[],"categories_sizes":[],"default_left":[0],"id":70,"left_children":[-1],"loss_changes":[0E0],"parents":[2147483647],"right_children":[-1],"split_conditions":[-5.549624E-3],"split_indices":[0],"split_type":[0],"sum_hessian":[1.7341493E0],"tree_param":{"num_deleted":"0","num_feature":"2048","num_nodes":"1","size_leaf_vector":"1"}},{"base_weights":[-5.2118074E-2],"categories":[],"categories_nodes":[],"categories_segments":[],"categories_sizes":[],"default_left":[0],"id":71,"left_children":[-1],"loss_changes":[0E0],"parents":[2147483647],"right_children":[-1],"split_conditions":[-5.2118073E-3],"split_indices":[0],"split_type":[0],"sum_hessian":[1.7270967E0],"tree_param":{"num_deleted":"0","num_feature":"2048","num_nodes":"1","size_leaf_vector":"1"}},{"base_weights":[-4.8942022E-2],"categories":[],"categories_nodes":[],"categories_segments":[],"categories_sizes":[],"default_left":[0],"id":72,"left_children":[-1],"loss_changes":[0E0],"parents":[2147483647],"right_children":[-1],"split_conditions":[-4.894202E-3],"split_indices":[0],"split_type":[0],"sum_hessian":[1.7205001E0],"tree_param":{"num_deleted":"0","num_feature":"2048","num_nodes":"1","size_leaf_vector":"1"}},{"base_weights":[-4.595665E-2],"categories":[],"categories_nodes":[],"categories_segments":[],"categories_sizes":[],"default_left":[0],"id":73,"left_children":[-1],"loss_changes":[0E0],"parents":[2147483647],"right_children":[-1],"split_conditions":[-4.595665E-3],"split_indices":[0],"split_type":[0],"sum_hessian":[1.7143291E0],"tree_param":{"num_deleted":"0","num_feature":"2048","num_nodes":"1","size_leaf_vector":"1"}},{"base_weights":[-4.3150738E-2],"categories":[],"categories_nodes":[],"categories_segments":[],"categories_sizes":[],"default_left":[0],"id":74,"left_children":[-1],"loss_changes":[0E0],"parents":[2147483647],"right_children":[-1],"split_conditions":[-4.315074E-3],"split_indices":[0],"split_type":[0],"sum_hessian":[1.7085552E0],"tree_param":{"num_deleted":"0","num_feature":"2048","num_nodes":"1","size_leaf_vector":"1"}},{"base_weights":[-4.0513948E-2],"categories":[],"categories_nodes":[],"categories_segments":[],"categories_sizes":[],"default_left":[0],"id":75,"left_children":[-1],"loss_changes":[0E0],"parents":[2147483647],"right_children":[-1],"split_conditions":[-4.0513948E-3],"split_indices":[0],"split_type":[0],"sum_hessian":[1.7031523E0],"tree_param":{"num_deleted":"0","num_feature":"2048","num_nodes":"1","size_leaf_vector":"1"}},{"base_weights":[-3.8036365E-2],"categories":[],"categories_nodes":[],"categories_segments":[],"categories_sizes":[],"default_left":[0],"id":76,"left_children":[-1],"loss_changes":[0E0],"parents":[2147483647],"right_children":[-1],"split_conditions":[-3.8036366E-3],"split_indices":[0],"split_type":[0],"sum_hessian":[1.6980954E0],"tree_param":{"num_deleted":"0","num_feature":"2048","num_nodes":"1","size_leaf_vector":"1"}},{"base_weights":[-3.570843E-2],"categories":[],"categories_nodes":[],"categories_segments":[],"categories_sizes":[],"default_left":[0],"id":77,"left_children":[-1],"loss_changes":[0E0],"parents":[2147483647],"right_children":[-1],"split_conditions":[-3.5708433E-3],"split_indices":[0],"split_type":[0],"sum_hessian":[1.6933615E0],"tree_param":{"num_deleted":"0","num_feature":"2048","num_nodes":"1","size_leaf_vector":"1"}},{"base_weights":[-3.3521403E-2],"categories":[],"categories_nodes":[],"categories_segments":[],"categories_sizes":[],"default_left":[0],"id":78,"left_children":[-1],"loss_changes":[0E0],"parents":[2147483647],"right_children":[-1],"split_conditions":[-3.3521403E-3],"split_indices":[0],"split_type":[0],"sum_hessian":[1.6889294E0],"tree_param":{"num_deleted":"0","num_feature":"2048","num_nodes":"1","size_leaf_vector":"1"}},{"base_weights":[-3.1467058E-2],"categories":[],"categories_nodes":[],"categories_segments":[],"categories_sizes":[],"default_left":[0],"id":79,"left_children":[-1],"loss_changes":[0E0],"parents":[2147483647],"right_children":[-1],"split_conditions":[-3.146706E-3],"split_indices":[0],"split_type":[0],"sum_hessian":[1.6847798E0],"tree_param":{"num_deleted":"0","num_feature":"2048","num_nodes":"1","size_leaf_vector":"1"}},{"base_weights":[-2.9537478E-2],"categories":[],"categories_nodes":[],"categories_segments":[],"categories_sizes":[],"default_left":[0],"id":80,"left_children":[-1],"loss_changes":[0E0],"parents":[2147483647],"right_children":[-1],"split_conditions":[-2.953748E-3],"split_indices":[0],"split_type":[0],"sum_hessian":[1.6808939E0],"tree_param":{"num_deleted":"0","num_feature":"2048","num_nodes":"1","size_leaf_vector":"1"}},{"base_weights":[-2.7725201E-2],"categories":[],"categories_nodes":[],"categories_segments":[],"categories_sizes":[],"default_left":[0],"id":81,"left_children":[-1],"loss_changes":[0E0],"parents":[2147483647],"right_children":[-1],"split_conditions":[-2.77252E-3],"split_indices":[0],"split_type":[0],"sum_hessian":[1.677255E0],"tree_param":{"num_deleted":"0","num_feature":"2048","num_nodes":"1","size_leaf_vector":"1"}},{"base_weights":[-2.602329E-2],"categories":[],"categories_nodes":[],"categories_segments":[],"categories_sizes":[],"default_left":[0],"id":82,"left_children":[-1],"loss_changes":[0E0],"parents":[2147483647],"right_children":[-1],"split_conditions":[-2.602329E-3],"split_indices":[0],"split_type":[0],"sum_hessian":[1.6738465E0],"tree_param":{"num_deleted":"0","num_feature":"2048","num_nodes":"1","size_leaf_vector":"1"}},{"base_weights":[-2.4424998E-2],"categories":[],"categories_nodes":[],"categories_segments":[],"categories_sizes":[],"default_left":[0],"id":83,"left_children":[-1],"loss_changes":[0E0],"parents":[2147483647],"right_children":[-1],"split_conditions":[-2.4424999E-3],"split_indices":[0],"split_type":[0],"sum_hessian":[1.6706537E0],"tree_param":{"num_deleted":"0","num_feature":"2048","num_nodes":"1","size_leaf_vector":"1"}},{"base_weights":[-2.2924218E-2],"categories":[],"categories_nodes":[],"categories_segments":[],"categories_sizes":[],"default_left":[0],"id":84,"left_children":[-1],"loss_changes":[0E0],"parents":[2147483647],"right_children":[-1],"split_conditions":[-2.2924219E-3],"split_indices":[0],"split_type":[0],"sum_hessian":[1.6676625E0],"tree_param":{"num_deleted":"0","num_feature":"2048","num_nodes":"1","size_leaf_vector":"1"}},{"base_weights":[-2.1514831E-2],"categories":[],"categories_nodes":[],"categories_segments":[],"categories_sizes":[],"default_left":[0],"id":85,"left_children":[-1],"loss_changes":[0E0],"parents":[2147483647],"right_children":[-1],"split_conditions":[-2.1514832E-3],"split_indices":[0],"split_type":[0],"sum_hessian":[1.6648598E0],"tree_param":{"num_deleted":"0","num_feature":"2048","num_nodes":"1","size_leaf_vector":"1"}},{"base_weights":[-2.0191627E-2],"categories":[],"categories_nodes":[],"categories_segments":[],"categories_sizes":[],"default_left":[0],"id":86,"left_children":[-1],"loss_changes":[0E0],"parents":[2147483647],"right_children":[-1],"split_conditions":[-2.0191628E-3],"split_indices":[0],"split_type":[0],"sum_hessian":[1.6622338E0],"tree_param":{"num_deleted":"0","num_feature":"2048","num_nodes":"1","size_leaf_vector":"1"}},{"base_weights":[-1.894947E-2],"categories":[],"categories_nodes":[],"categories_segments":[],"categories_sizes":[],"default_left":[0],"id":87,"left_children":[-1],"loss_changes":[0E0],"parents":[2147483647],"right_children":[-1],"split_conditions":[-1.894947E-3],"split_indices":[0],"split_type":[0],"sum_hessian":[1.6597735E0],"tree_param":{"num_deleted":"0","num_feature":"2048","num_nodes":"1","size_leaf_vector":"1"}},{"base_weights":[-1.7783208E-2],"categories":[],"categories_nodes":[],"categories_segments":[],"categories_sizes":[],"default_left":[0],"id":88,"left_children":[-1],"loss_changes":[0E0],"parents":[2147483647],"right_children":[-1],"split_conditions":[-1.7783208E-3],"split_indices":[0],"split_type":[0],"sum_hessian":[1.6574676E0],"tree_param":{"num_deleted":"0","num_feature":"2048","num_nodes":"1","size_leaf_vector":"1"}},{"base_weights":[-1.6688466E-2],"categories":[],"categories_nodes":[],"categories_segments":[],"categories_sizes":[],"default_left":[0],"id":89,"left_children":[-1],"loss_changes":[0E0],"parents":[2147483647],"right_children":[-1],"split_conditions":[-1.6688466E-3],"split_indices":[0],"split_type":[0],"sum_hessian":[1.6553067E0],"tree_param":{"num_deleted":"0","num_feature":"2048","num_nodes":"1","size_leaf_vector":"1"}},{"base_weights":[-1.5660604E-2],"categories":[],"categories_nodes":[],"categories_segments":[],"categories_sizes":[],"default_left":[0],"id":90,"left_children":[-1],"loss_changes":[0E0],"parents":[2147483647],"right_children":[-1],"split_conditions":[-1.5660605E-3],"split_indices":[0],"split_type":[0],"sum_hessian":[1.6532813E0],"tree_param":{"num_deleted":"0","num_feature":"2048","num_nodes":"1","size_leaf_vector":"1"}},{"base_weights":[-1.4695952E-2],"categories":[],"categories_nodes":[],"categories_segments":[],"categories_sizes":[],"default_left":[0],"id":91,"left_children":[-1],"loss_changes":[0E0],"parents":[2147483647],"right_children":[-1],"split_conditions":[-1.4695952E-3],"split_indices":[0],"split_type":[0],"sum_hessian":[1.651383E0],"tree_param":{"num_deleted":"0","num_feature":"2048","num_nodes":"1","size_leaf_vector":"1"}},{"base_weights":[-1.3790347E-2],"categories":[],"categories_nodes":[],"categories_segments":[],"categories_sizes":[],"default_left":[0],"id":92,"left_children":[-1],"loss_changes":[0E0],"parents":[2147483647],"right_children":[-1],"split_conditions":[-1.3790347E-3],"split_indices":[0],"split_type":[0],"sum_hessian":[1.6496036E0],"tree_param":{"num_deleted":"0","num_feature":"2048","num_nodes":"1","size_leaf_vector":"1"}},{"base_weights":[-1.2940393E-2],"categories":[],"categories_nodes":[],"categories_segments":[],"categories_sizes":[],"default_left":[0],"id":93,"left_children":[-1],"loss_changes":[0E0],"parents":[2147483647],"right_children":[-1],"split_conditions":[-1.2940393E-3],"split_indices":[0],"split_type":[0],"sum_hessian":[1.6479356E0],"tree_param":{"num_deleted":"0","num_feature":"2048","num_nodes":"1","size_leaf_vector":"1"}},{"base_weights":[-1.2142553E-2],"categories":[],"categories_nodes":[],"categories_segments":[],"categories_sizes":[],"default_left":[0],"id":94,"left_children":[-1],"loss_changes":[0E0],"parents":[2147483647],"right_children":[-1],"split_conditions":[-1.2142553E-3],"split_indices":[0],"split_type":[0],"sum_hessian":[1.6463718E0],"tree_param":{"num_deleted":"0","num_feature":"2048","num_nodes":"1","size_leaf_vector":"1"}},{"base_weights":[-1.1393867E-2],"categories":[],"categories_nodes":[],"categories_segments":[],"categories_sizes":[],"default_left":[0],"id":95,"left_children":[-1],"loss_changes":[0E0],"parents":[2147483647],"right_children":[-1],"split_conditions":[-1.1393868E-3],"split_indices":[0],"split_type":[0],"sum_hessian":[1.6449062E0],"tree_param":{"num_deleted":"0","num_feature":"2048","num_nodes":"1","size_leaf_vector":"1"}},{"base_weights":[-1.0691212E-2],"categories":[],"categories_nodes":[],"categories_segments":[],"categories_sizes":[],"default_left":[0],"id":96,"left_children":[-1],"loss_changes":[0E0],"parents":[2147483647],"right_children":[-1],"split_conditions":[-1.0691212E-3],"split_indices":[0],"split_type":[0],"sum_hessian":[1.643532E0],"tree_param":{"num_deleted":"0","num_feature":"2048","num_nodes":"1","size_leaf_vector":"1"}},{"base_weights":[-1.0031715E-2],"categories":[],"categories_nodes":[],"categories_segments":[],"categories_sizes":[],"default_left":[0],"id":97,"left_children":[-1],"loss_changes":[0E0],"parents":[2147483647],"right_children":[-1],"split_conditions":[-1.0031716E-3],"split_indices":[0],"split_type":[0],"sum_hessian":[1.6422436E0],"tree_param":{"num_deleted":"0","num_feature":"2048","num_nodes":"1","size_leaf_vector":"1"}},{"base_weights":[-9.412698E-3],"categories":[],"categories_nodes":[],"categories_segments":[],"categories_sizes":[],"default_left":[0],"id":98,"left_children":[-1],"loss_changes":[0E0],"parents":[2147483647],"right_children":[-1],"split_conditions":[-9.4126986E-4],"split_indices":[0],"split_type":[0],"sum_hessian":[1.6410354E0],"tree_param":{"num_deleted":"0","num_feature":"2048","num_nodes":"1","size_leaf_vector":"1"}},{"base_weights":[-8.831776E-3],"categories":[],"categories_nodes":[],"categories_segments":[],"categories_sizes":[],"default_left":[0],"id":99,"left_children":[-1],"loss_changes":[0E0],"parents":[2147483647],"right_children":[-1],"split_conditions":[-8.8317756E-4],"split_indices":[0],"split_type":[0],"sum_hessian":[1.6399027E0],"tree_param":{"num_deleted":"0","num_feature":"2048","num_nodes":"1","size_leaf_vector":"1"}}]},"name":"gbtree"},"learner_model_param":{"base_score":"1.2185286E-1","boost_from_average":"1","num_class":"0","num_feature":"2048","num_target":"1"},"objective":{"name":"binary:logistic","reg_loss_param":{"scale_pos_weight":"1"}}},"version":[2,0,1]}